Workbook

Sheet Operating Model
E2: Units | F2: Constants | G2: Constants | H2: Constants
C3: COPART
C4: Three Statement Model
D5: Forecast Period Start | G5: 45869
D6: Forecast Period | G6: 10
D7: Forecast Period End | G7: =EDATE(G5,G6*12) -> 49521
D8: Beginning Period | I8: =IF(H11,H8,H9+1) -> 44409 | J8: =IF(I11,I8,I9+1) -> 44774 | K8: =IF(J11,J8,J9+1) -> 45139 | L8: =IF(K11,K8,K9+1) -> 45505 | M8: =IF(L11,L8,L9+1) -> 45505 | N8: =IF(M11,M8,M9+1) -> 45870 | O8: =IF(N11,N8,N9+1) -> 46235 | P8: =IF(O11,O8,O9+1) -> 46600 | ... AH8: =IF(AG11,AG8,AG9+1) -> 53175
D9: Ending Period | H9: 44408 | I9: =EDATE(I8,12)-1 -> 44773 | J9: =EDATE(J8,12)-1 -> 45138 | K9: =EDATE(K8,12)-1 -> 45504 | L9: =EDATE(L8,12)-1 -> 45869 | M9: =EDATE(M8,12)-1 -> 45869 | N9: =EDATE(N8,12)-1 -> 46234 | O9: =EDATE(O8,12)-1 -> 46599 | P9: =EDATE(P8,12)-1 -> 46965 | ... AH9: =EDATE(AH8,12)-1 -> 53539
D10: Forecast Flag | I10: =AND(I9>$G$5,I9<=$G$7) -> FALSE | J10: =AND(J9>$G$5,J9<=$G$7) -> FALSE | K10: =AND(K9>$G$5,K9<=$G$7) -> FALSE | L10: =AND(L9>$G$5,L9<=$G$7) -> FALSE | M10: =AND(M9>$G$5,M9<=$G$7) -> FALSE | N10: =AND(N9>$G$5,N9<=$G$7) -> TRUE | O10: =AND(O9>$G$5,O9<=$G$7) -> TRUE | P10: =AND(P9>$G$5,P9<=$G$7) -> TRUE | ... AH10: =AND(AH9>$G$5,AH9<=$G$7) -> FALSE
D11: Preceeds TTM | I11: =AND(NOT(H11),I9=$G$5) -> FALSE | J11: =AND(NOT(I11),J9=$G$5) -> FALSE | K11: =AND(NOT(J11),K9=$G$5) -> FALSE | L11: =AND(NOT(K11),L9=$G$5) -> TRUE | M11: =AND(NOT(L11),M9=$G$5) -> FALSE | N11: =AND(NOT(M11),N9=$G$5) -> FALSE | O11: =AND(NOT(N11),O9=$G$5) -> FALSE | P11: =AND(NOT(O11),P9=$G$5) -> FALSE | ... AH11: =AND(NOT(AG11),AH9=$G$5) -> FALSE
D12: Period Labels | I12: =IF(AND(I9=$G$5,H11), "TTM", IF(I9<=$G$5, "Historical", IF(I9>$G$7, "", "Forecast"))) -> Historical | J12: =IF(AND(J9=$G$5,I11), "TTM", IF(J9<=$G$5, "Historical", IF(J9>$G$7, "", "Forecast"))) -> Historical | K12: =IF(AND(K9=$G$5,J11), "TTM", IF(K9<=$G$5, "Historical", IF(K9>$G$7, "", "Forecast"))) -> Historical | L12: =IF(AND(L9=$G$5,K11), "TTM", IF(L9<=$G$5, "Historical", IF(L9>$G$7, "", "Forecast"))) -> Historical | M12: =IF(AND(M9=$G$5,L11), "", IF(M9<=$G$5, "Historical", IF(M9>$G$7, "", "Forecast"))) | N12: =IF(AND(N9=$G$5,M11), "TTM", IF(N9<=$G$5, "Historical", IF(N9>$G$7, "", "Forecast"))) -> Forecast | O12: =IF(AND(O9=$G$5,N11), "TTM", IF(O9<=$G$5, "Historical", IF(O9>$G$7, "", "Forecast"))) -> Forecast | P12: =IF(AND(P9=$G$5,O11), "TTM", IF(P9<=$G$5, "Historical", IF(P9>$G$7, "", "Forecast"))) -> Forecast | Q12: =IF(AND(Q9=$G$5,P11), "TTM", IF(Q9<=$G$5, "Historical", IF(Q9>$G$7, "", "Forecast"))) -> Forecast | R12: =IF(AND(R9=$G$5,Q11), "TTM", IF(R9<=$G$5, "Historical", IF(R9>$G$7, "", "Forecast"))) -> Forecast | S12: =IF(AND(S9=$G$5,R11), "TTM", IF(S9<=$G$5, "Historical", IF(S9>$G$7, "", "Forecast"))) -> Forecast | T12: =IF(AND(T9=$G$5,S11), "TTM", IF(T9<=$G$5, "Historical", IF(T9>$G$7, "", "Forecast"))) -> Forecast | U12: =IF(AND(U9=$G$5,T11), "TTM", IF(U9<=$G$5, "Historical", IF(U9>$G$7, "", "Forecast"))) -> Forecast | ... AH12: =IF(AND(AH9=$G$5,AG11), "TTM", IF(AH9<=$G$5, "Historical", IF(AH9>$G$7, "", "Forecast")))
C14: Revenue Build
C16: Market Size | K16: 10600000 | L16: =R16/(1+F17)^5 -> 12196309 | M16: =L16 -> 12196309 | N16: 14100000 | O16: =N16+($R$16-$N$16)/4 -> 17375000 | P16: =O16+($R$16-$N$16)/4 -> 20650000 | Q16: =P16+($R$16-$N$16)/4 -> 23925000 | R16: 27200000
D17: Market Growth CAGR (2025-2030) | F17: 0.174
D18: Implied market shares | K18: =K65/K16 -> 0.39970028 | L18: =L65/L16 -> 0.38101347 | M18: =M65/M16 -> 0.38101347 | N18: =N65/N16 -> 0.35045492 | O18: =O65/O16 -> 0.30197357 | P18: =P65/P16 -> 0.26941281 | Q18: =Q65/Q16 -> 0.24624704 | R18: =R65/R16 -> 0.22909383
C20: Total Vehicles on Road - US | I20: 284000 | J20: 286000 | K20: 289000 | L20: 293000 | M20: =L20 -> 293000 | N20: =M20*(1+N21)*N10 -> 295930 | O20: =N20*(1+O21)*O10 -> 298889.3 | P20: =O20*(1+P21)*P10 -> 301878.19 | Q20: =P20*(1+Q21)*Q10 -> 304896.97 | R20: =Q20*(1+R21)*R10 -> 307945.94 | S20: =R20*(1+S21)*S10 -> 311025.4 | T20: =S20*(1+T21)*T10 -> 314135.66 | U20: =T20*(1+U21)*U10 -> 317277.01 | ... W20: =V20*(1+W21)*W10 -> 323654.28
D21: Growth Rate | J21: =J20/I20-1 -> 0.0070422535 | K21: =K20/J20-1 -> 0.01048951 | L21: =L20/K20-1 -> 0.01384083 | M21: 0 | N21: 0.01 | O21: =N21*O10 -> 0.01 | P21: =O21*P10 -> 0.01 | Q21: =P21*Q10 -> 0.01 | R21: =Q21*R10 -> 0.01 | S21: =R21*S10 -> 0.01 | T21: =S21*T10 -> 0.01 | U21: =T21*U10 -> 0.01 | V21: =U21*V10 -> 0.01 | W21: =V21*W10 -> 0.01
C22: Total Loss Frequency | I22: 0.228 | J22: 0.192 | K22: 0.221 | L22: 0.228 | M22: =L22 -> 0.228 | N22: 0.231 | O22: =(N22+0.3%)*O10 -> 0.234 | P22: =(O22+0.3%)*P10 -> 0.237 | Q22: =(P22+0.3%)*Q10 -> 0.24 | R22: =(Q22+0.3%)*R10 -> 0.243 | S22: =(R22+0.3%)*S10 -> 0.246 | T22: =(S22+0.3%)*T10 -> 0.249 | U22: =(T22+0.3%)*U10 -> 0.252 | V22: =(U22+0.3%)*V10 -> 0.255 | W22: =(V22+0.3%)*W10 -> 0.258 | X22: 0 | Y22: 0 | Z22: 0 | AA22: 0 | AB22: 0 | AC22: 0 | AD22: 0 | AE22: 0 | AF22: 0 | AG22: 0 | AH22: 0
D23: Scaler | I23: 0.06 | J23: 0.06 | K23: 0.06 | L23: 0.06 | M23: 0.06 | N23: =DCF!G10 -> 0.06 | O23: =N23 -> 0.06 | P23: =O23 -> 0.06 | Q23: =P23 -> 0.06 | R23: =Q23 -> 0.06 | S23: =R23 -> 0.06 | T23: =S23 -> 0.06 | U23: =T23 -> 0.06 | V23: =U23 -> 0.06 | W23: =V23 -> 0.06
C24: Units Sold | I24: =I20*I22*I23 -> 3885.12 | J24: =J20*J22*J23 -> 3294.72 | K24: =K20*K22*K23 -> 3832.14 | L24: =L20*L22*L23 -> 4008.24 | M24: =M20*M22*M23 -> 4008.24 | N24: =N20*N22*N23 -> 4101.5898 | O24: =O20*O22*O23 -> 4196.4058 | P24: =P20*P22*P23 -> 4292.7079 | ... W24: =W20*W22*W23 -> 5010.1683
C25: Units sold Growth | J25: =J24/I24-1 -> -0.15196442 | K25: =K24/J24-1 -> 0.16311553 | L25: =L24/K24-1 -> 0.045953436 | M25: =M24/L24-1 -> 0 | N25: =N24/M24-1 -> 0.023289474 | O25: =O24/N24-1 -> 0.023116883 | P25: =P24/O24-1 -> 0.022948718 | Q25: =Q24/P24-1 -> 0.02278481 | ... W25: =W24/V24-1 -> 0.021882353
C26: Revenue Per Vehicle | L26: =L61/L24 -> 990.12584 | M26: =M61/M24 -> 990.12584 | N26: =M26+($W$26-$M$26)/10 -> 1031.1133 | O26: =N26+($W$26-$M$26)/10 -> 1072.1007 | P26: =O26+($W$26-$M$26)/10 -> 1113.0881 | Q26: =P26+($W$26-$M$26)/10 -> 1154.0755 | R26: =Q26+($W$26-$M$26)/10 -> 1195.0629 | S26: =R26+($W$26-$M$26)/10 -> 1236.0503 | T26: =S26+($W$26-$M$26)/10 -> 1277.0378 | U26: =T26+($W$26-$M$26)/10 -> 1318.0252 | V26: =U26+($W$26-$M$26)/10 -> 1359.0126 | W26: 1400
C28: Income Statement
C30: =C58 -> Service revenues and vehicle sales:
C31: =C59 -> 0 | D31: =D59 -> United States | J31: =J59/I59-1 -> 0.12177493 | K31: =K59/J59-1 -> 0.10010448 | L31: =L59/K59-1 -> 0.10410921 | N31: =(N59/M59-1)*N10 -> 0.065649737 | O31: =(O59/N59-1)*O10 -> 0.057670636 | P31: =(P59/O59-1)*P10 -> 0.055915843 | Q31: =(Q59/P59-1)*Q10 -> 0.054279456 | R31: =(R59/Q59-1)*R10 -> 0.052749098 | S31: =(S59/R59-1)*S10 -> 0.051314074 | T31: =(T59/S59-1)*T10 -> 0.049965095 | U31: =(U59/T59-1)*U10 -> 0.048694052 | ... AH31: =(AH59/AG59-1)*AH10 -> #DIV/0!
C32: =C60 -> 0 | D32: =D60 -> International | J32: =J60/I60-1 -> 0.11445721 | K32: =K60/J60-1 -> 0.21996034 | L32: =L60/K60-1 -> 0.18901817 | N32: =(N60/M60-1)*N10 -> 0.065649737 | O32: =(O60/N60-1)*O10 -> 0.1046081 | P32: =(P60/O60-1)*P10 -> 0.10130616 | Q32: =(Q60/P60-1)*Q10 -> 0.098239957 | R32: =(R60/Q60-1)*R10 -> 0.095384617 | S32: =(S60/R60-1)*S10 -> 0.092718673 | T32: =(T60/S60-1)*T10 -> 0.090223497 | U32: =(U60/T60-1)*U10 -> 0.087882842 | ... AH32: =(AH60/AG60-1)*AH10 -> #DIV/0!
C33: =C61 -> Service revenues | J33: =J61/I61-1 -> 0.12095449 | K33: =K61/J61-1 -> 0.1134645 | L33: =L61/K61-1 -> 0.11447901 | N33: =(N61/M61-1)*N10 -> 0.065649737 | O33: =(O61/N61-1)*O10 -> 0.063786438 | P33: =(P61/O61-1)*P10 -> 0.062057008 | Q33: =(Q61/P61-1)*Q10 -> 0.060446974 | R33: =(R61/Q61-1)*R10 -> 0.058943903 | S33: =(S61/R61-1)*S10 -> 0.057537053 | T33: =(T61/S61-1)*T10 -> 0.056217096 | U33: =(U61/T61-1)*U10 -> 0.05497589 | ... AH33: =(AH61/AG61-1)*AH10 -> #DIV/0!
C34: =C62 -> 0 | D34: =D62 -> United States | J34: =J62/I62-1 -> -0.15529206 | K34: =K62/J62-1 -> -0.02693624 | L34: =L62/K62-1 -> 0.1916913 | N34: 0.05 | O34: =N34*O10 -> 0.05 | P34: =O34*P10 -> 0.05 | Q34: =P34*Q10 -> 0.05 | R34: =Q34*R10 -> 0.05 | S34: =R34*S10 -> 0.05 | T34: =S34*T10 -> 0.05 | U34: =T34*U10 -> 0.05 | V34: =U34*V10 -> 0.05 | ... AH34: =AG34*AH10 -> 0
C35: =C63 -> 0 | D35: =D63 -> International | J35: =J63/I63-1 -> 0.37087106 | K35: =K63/J63-1 -> 0.042689319 | L35: =L63/K63-1 -> -0.18517266 | N35: 0.05 | O35: =N35*O10 -> 0.05 | P35: =O35*P10 -> 0.05 | Q35: =P35*Q10 -> 0.05 | R35: =Q35*R10 -> 0.05 | S35: =R35*S10 -> 0.05 | T35: =S35*T10 -> 0.05 | U35: =T35*U10 -> 0.05 | V35: =U35*V10 -> 0.05 | ... AH35: =AG35*AH10 -> 0
C36: =C64 -> Vehicle sales | J36: =J64/I64-1 -> 0.036285985 | K36: =K64/J64-1 -> 0.0065997408 | L36: =L64/K64-1 -> 0.0036622123 | N36: =N64/M64-1 -> 0.05 | O36: =O64/N64-1 -> 0.05 | P36: =P64/O64-1 -> 0.05 | Q36: =Q64/P64-1 -> 0.05 | R36: =R64/Q64-1 -> 0.05 | S36: =S64/R64-1 -> 0.05 | T36: =T64/S64-1 -> 0.05 | U36: =U64/T64-1 -> 0.05 | ... AH36: =AH64/AG64-1 -> #DIV/0!
C37: =C65 -> Total service revenues and vehicle sales | J37: =J65/I65-1 -> 0.10528572 | K37: =K65/J65-1 -> 0.094922675 | L37: =L65/K65-1 -> 0.096802486 | N37: =N65/M65-1 -> 0.063365414 | O37: =O65/N65-1 -> 0.061799386 | P37: =P65/O65-1 -> 0.060338532 | Q37: =Q65/P65-1 -> 0.058972493 | R37: =R65/Q65-1 -> 0.05769226 | S37: =S65/R65-1 -> 0.056489961 | T37: =T65/S65-1 -> 0.055358686 | U37: =U65/T65-1 -> 0.054292345 | ... AH37: =AH65/AG65-1 -> #DIV/0!
C39: Historical CAGR | F39: =((L65/I65)^(1/3))-1 -> 0.098994398
C40: Forecasted CAGR | F40: =((W65/M65)^(1/10))-1 -> 0.057386981
C42: =C66 -> Operating expenses:
C43: =C67 -> Facility operations | I43: =I67/I$65 -> -0.37404357 | J43: =J67/J$65 -> -0.39230442 | K43: =K67/K$65 -> -0.40362413 | L43: =L67/L$65 -> -0.41840662 | M43: =L43 -> -0.41840662 | N43: =M43-1% -> -0.42840662 | O43: =N43-1% -> -0.43840662 | P43: =O43-1% -> -0.44840662 | Q43: =P43-1% -> -0.45840662 | R43: =Q43-1% -> -0.46840662 | S43: =R43-1% -> -0.47840662 | T43: =S43-1% -> -0.48840662 | U43: =T43-1% -> -0.49840662 | ... AH43: =AG43-1% -> -0.62840662
C44: =C68 -> Cost of vehicle sales | I44: =I68/I$65 -> -0.16715687 | J44: =J68/J$65 -> -0.15880479 | K44: =K68/K$65 -> -0.14621498 | L44: =L68/L$65 -> -0.12976166 | N44: -0.14 | O44: =N44 -> -0.14 | P44: =O44 -> -0.14 | Q44: =P44 -> -0.14 | R44: =Q44 -> -0.14 | S44: =R44 -> -0.14 | T44: =S44 -> -0.14 | U44: =T44 -> -0.14 | V44: =U44 -> -0.14 | ... AH44: =AG44 -> -0.14
C45: =C69 -> General and administrative | I45: =I69/I$65 -> -0.06604662 | J45: =J69/J$65 -> -0.064716587 | K45: =K69/K$65 -> -0.079122729 | L45: =L69/L$65 -> -0.086708122 | N45: =L45 -> -0.086708122 | O45: =N45 -> -0.086708122 | P45: =O45 -> -0.086708122 | Q45: =P45 -> -0.086708122 | R45: =Q45 -> -0.086708122 | S45: =R45 -> -0.086708122 | T45: =S45 -> -0.086708122 | U45: =T45 -> -0.086708122 | V45: =U45 -> -0.086708122 | ... AH45: =AG45 -> -0.086708122
C46: =C70 -> Total operating expenses | I46: =I70/I$65 -> -0.60724706 | J46: =J70/J$65 -> -0.6158258 | K46: =K70/K$65 -> -0.62896184 | L46: =L70/L$65 -> -0.63487641 | N46: =N70/N$65 -> -0.65511474 | O46: =O70/O$65 -> -0.66511474 | P46: =P70/P$65 -> -0.67511474 | Q46: =Q70/Q$65 -> -0.68511474 | R46: =R70/R$65 -> -0.69511474 | S46: =S70/S$65 -> -0.70511474 | T46: =T70/T$65 -> -0.71511474 | U46: =U70/U$65 -> -0.72511474 | ... AH46: =AH70/AH$65 -> #DIV/0!
C48: Effective tax rate | I48: =I77/I76 -> -0.18704892 | J48: =J77/J76 -> -0.20368095 | K48: =K77/K76 -> -0.20544372 | L48: =L77/L76 -> -0.18317234 | N48: =AVERAGE(I48:L48) -> -0.19483648 | O48: =N48 -> -0.19483648 | P48: =O48 -> -0.19483648 | Q48: =P48 -> -0.19483648 | R48: =Q48 -> -0.19483648 | S48: =R48 -> -0.19483648 | T48: =S48 -> -0.19483648 | U48: =T48 -> -0.19483648 | V48: =U48 -> -0.19483648 | ... AH48: =AG48 -> -0.19483648
C50: US % of Total Service Rev | I50: =I59/I$61 -> 0.88788275 | J50: =J59/J$61 -> 0.8885326 | K50: =K59/K$61 -> 0.87787145 | L50: =L59/L$61 -> 0.86970319 | N50: =L50 -> 0.86970319 | O50: =N50-0.5% -> 0.86470319 | P50: =O50-0.5% -> 0.85970319 | Q50: =P50-0.5% -> 0.85470319 | R50: =Q50-0.5% -> 0.84970319 | S50: =R50-0.5% -> 0.84470319 | T50: =S50-0.5% -> 0.83970319 | U50: =T50-0.5% -> 0.83470319 | V50: =U50-0.5% -> 0.82970319 | W50: =V50-0.5% -> 0.82470319 | X50: =W50 -> 0.82470319 | Y50: =X50 -> 0.82470319 | Z50: =Y50 -> 0.82470319 | AA50: =Z50 -> 0.82470319 | AB50: =AA50 -> 0.82470319 | AC50: =AB50 -> 0.82470319 | AD50: =AC50 -> 0.82470319 | AE50: =AD50 -> 0.82470319 | ... AH50: =AG50 -> 0.82470319
C51: International % of Total Service Rev | I51: =I60/I$61 -> 0.11211725 | J51: =J60/J$61 -> 0.1114674 | K51: =K60/K$61 -> 0.12212855 | L51: =L60/L$61 -> 0.13029681 | N51: =L51 -> 0.13029681 | O51: =N51+0.5% -> 0.13529681 | P51: =O51+0.5% -> 0.14029681 | Q51: =P51+0.5% -> 0.14529681 | R51: =Q51+0.5% -> 0.15029681 | S51: =R51+0.5% -> 0.15529681 | T51: =S51+0.5% -> 0.16029681 | U51: =T51+0.5% -> 0.16529681 | V51: =U51+0.5% -> 0.17029681 | W51: =V51+0.5% -> 0.17529681 | X51: =W51 -> 0.17529681 | Y51: =X51 -> 0.17529681 | Z51: =Y51 -> 0.17529681 | AA51: =Z51 -> 0.17529681 | AB51: =AA51 -> 0.17529681 | AC51: =AB51 -> 0.17529681 | AD51: =AC51 -> 0.17529681 | AE51: =AD51 -> 0.17529681 | ... AH51: =AG51 -> 0.17529681
C53: Operating Margin | I53: =I71/I$65 -> 0.39275294 | J53: =J71/J$65 -> 0.3841742 | K53: =K71/K$65 -> 0.37103816 | L53: =L71/L$65 -> 0.36512359 | M53: =M71/M$65 -> 0.36512359 | N53: =N71/N$65 -> 0.34488526 | O53: =O71/O$65 -> 0.33488526 | P53: =P71/P$65 -> 0.32488526 | ... W53: =W71/W$65 -> 0.25488526
C54: Pre tax Margin | I54: =I76/I$65 -> 0.38302892 | J54: =J76/J$65 -> 0.40168517 | K54: =K76/K$65 -> 0.40469026 | L54: =L76/L$65 -> 0.40791869 | M54: =M76/M$65 -> 0.36512359 | N54: =N76/N$65 -> 0.34488526 | O54: =O76/O$65 -> 0.33488526 | P54: =P76/P$65 -> 0.32488526 | ... W54: =W76/W$65 -> 0.25488526
C55: Net Margin | I55: =I78/I$65 -> 0.31138378 | J55: =J78/J$65 -> 0.31986955 | K55: =K78/K$65 -> 0.32154919 | L55: =L78/L$65 -> 0.33319927 | M55: =M78/M$65 -> 0.29040417 | N55: =N78/N$65 -> 0.27768903 | O55: =O78/O$65 -> 0.26963739 | P55: =P78/P$65 -> 0.26158576 | ... W55: =W78/W$65 -> 0.20522431
C58: Service revenues and vehicle sales:
D59: United States | I59: 2533165 | J59: 2841641 | K59: 3126102 | L59: 3451558 | M59: =L59 -> 3451558 | N59: =N50*N$61 -> 3678151.9 | O59: =O50*O$61 -> 3890273.2 | P59: =P50*P$61 -> 4107801.1 | Q59: =Q50*Q$61 -> 4330770.4 | R59: =R50*R$61 -> 4559214.6 | S59: =S50*S$61 -> 4793166.5 | T59: =T50*T$61 -> 5032657.5 | U59: =U50*U$61 -> 5277718 | ... AH59: =AH50*AH$61 -> 0
D60: International | I60: 319875 | J60: 356487 | K60: 434900 | L60: 517104 | M60: =L60 -> 517104 | N60: =N51*N$61 -> 551051.74 | O60: =O51*O$61 -> 608696.22 | P60: =P51*P$61 -> 670360.89 | Q60: =Q51*Q$61 -> 736217.12 | R60: =R51*R$61 -> 806440.91 | S60: =S51*S$61 -> 881213.04 | T60: =T51*T$61 -> 960719.16 | U60: =U51*U$61 -> 1045149.9 | ... AH60: =AH51*AH$61 -> 0
C61: Service revenues | I61: =SUM(I59:I60) -> 2853040 | J61: =SUM(J59:J60) -> 3198128 | K61: =SUM(K59:K60) -> 3561002 | L61: =SUM(L59:L60) -> 3968662 | M61: =SUM(M59:M60) -> 3968662 | N61: =N26*N24 -> 4229203.6 | O61: =O26*O24 -> 4498969.5 | P61: =P26*P24 -> 4778162 | Q61: =Q26*Q24 -> 5066987.5 | R61: =R26*R24 -> 5365655.5 | S61: =S26*S24 -> 5674379.5 | T61: =T26*T24 -> 5993376.6 | U61: =U26*U24 -> 6322867.9 | ... AH61: =AH26*AH24 -> 0
D62: United States | I62: 411985 | J62: 348007 | K62: 338633 | L62: 403546 | M62: =L62 -> 403546 | N62: =M62*(1+N34)*N10 -> 423723.3 | O62: =N62*(1+O34)*O10 -> 444909.47 | P62: =O62*(1+P34)*P10 -> 467154.94 | Q62: =P62*(1+Q34)*Q10 -> 490512.69 | R62: =Q62*(1+R34)*R10 -> 515038.32 | S62: =R62*(1+S34)*S10 -> 540790.24 | T62: =S62*(1+T34)*T10 -> 567829.75 | U62: =T62*(1+U34)*U10 -> 596221.23 | ... AH62: =AG62*(1+AH34)*AH10 -> 0
D63: International | I63: 235896 | J63: 323383 | K63: 337188 | L63: 274750 | M63: =L63 -> 274750 | N63: =M63*(1+N35)*N10 -> 288487.5 | O63: =N63*(1+O35)*O10 -> 302911.88 | P63: =O63*(1+P35)*P10 -> 318057.47 | Q63: =P63*(1+Q35)*Q10 -> 333960.34 | R63: =Q63*(1+R35)*R10 -> 350658.36 | S63: =R63*(1+S35)*S10 -> 368191.28 | T63: =S63*(1+T35)*T10 -> 386600.84 | U63: =T63*(1+U35)*U10 -> 405930.88 | ... AH63: =AG63*(1+AH35)*AH10 -> 0
C64: Vehicle sales | I64: =SUM(I62:I63) -> 647881 | J64: =SUM(J62:J63) -> 671390 | K64: =SUM(K62:K63) -> 675821 | L64: =SUM(L62:L63) -> 678296 | M64: =SUM(M62:M63) -> 678296 | N64: =SUM(N62:N63) -> 712210.8 | O64: =SUM(O62:O63) -> 747821.34 | P64: =SUM(P62:P63) -> 785212.41 | ... AH64: =SUM(AH62:AH63) -> 0
C65: Total service revenues and vehicle sales | I65: =I61+I64 -> 3500921 | J65: =J61+J64 -> 3869518 | K65: =K61+K64 -> 4236823 | L65: =L61+L64 -> 4646958 | M65: =M61+M64 -> 4646958 | N65: =N61+N64 -> 4941414.4 | O65: =O61+O64 -> 5246790.8 | P65: =P61+P64 -> 5563374.4 | ... AH65: =AH61+AH64 -> 0
C66: Operating expenses:
C67: Facility operations | I67: -1309497 | J67: -1518029 | K67: -1710084 | L67: -1944318 | M67: =L67 -> -1944318 | N67: =N$65*N43 -> -2116934.7 | O67: =O$65*O43 -> -2300227.8 | P67: =P$65*P43 -> -2494653.9 | Q67: =Q$65*Q43 -> -2700684.5 | R67: =R$65*R43 -> -2918806.6 | S67: =S$65*S43 -> -3149523.5 | T67: =T$65*T43 -> -3393355.1 | U67: =U$65*U43 -> -3650838.5 | ... AH67: =AH$65*AH43 -> 0
C68: Cost of vehicle sales | I68: -585203 | J68: -614498 | K68: -619487 | L68: -602997 | M68: =L68 -> -602997 | N68: =N$65*N44 -> -691798.02 | O68: =O$65*O44 -> -734550.71 | P68: =P$65*P44 -> -778872.42 | Q68: =Q$65*Q44 -> -824804.47 | R68: =R$65*R44 -> -872389.3 | S68: =S$65*S44 -> -921670.54 | T68: =T$65*T44 -> -972693.01 | U68: =U$65*U44 -> -1025502.8 | ... AH68: =AH$65*AH44 -> 0
C69: General and administrative | I69: -231224 | J69: -250422 | K69: -335229 | L69: -402929 | M69: =L69 -> -402929 | N69: =N$65*N45 -> -428460.76 | O69: =O$65*O45 -> -454939.37 | P69: =P$65*P45 -> -482389.75 | Q69: =Q$65*Q45 -> -510837.47 | R69: =R$65*R45 -> -540308.84 | S69: =S$65*S45 -> -570830.87 | T69: =T$65*T45 -> -602431.31 | U69: =U$65*U45 -> -635138.72 | ... AH69: =AH$65*AH45 -> 0
C70: Total operating expenses | I70: =SUM(I67:I69) -> -2125924 | J70: =SUM(J67:J69) -> -2382949 | K70: =SUM(K67:K69) -> -2664800 | L70: =SUM(L67:L69) -> -2950244 | M70: =SUM(M67:M69) -> -2950244 | N70: =SUM(N67:N69) -> -3237193.4 | O70: =SUM(O67:O69) -> -3489717.9 | P70: =SUM(P67:P69) -> -3755916.1 | ... AH70: =SUM(AH67:AH69) -> 0
C71: Operating income | I71: =I65+I70 -> 1374997 | J71: =J65+J70 -> 1486569 | K71: =K65+K70 -> 1572023 | L71: =L65+L70 -> 1696714 | M71: =M65+M70 -> 1696714 | N71: =N65+N70 -> 1704221 | O71: =O65+O70 -> 1757072.9 | P71: =P65+P70 -> 1807458.3 | ... AH71: =AH65+AH70 -> 0
C72: Other income (expense):
C73: Interest income (expense), net | I73: -16688 | J73: 65928 | K73: 145673 | L73: 178909 | M73: 0 | N73: 0 | O73: 0 | P73: 0 | Q73: 0 | R73: 0 | S73: 0 | T73: 0 | U73: 0 | V73: 0 | W73: 0 | X73: 0 | Y73: 0 | Z73: 0 | AA73: 0 | AB73: 0 | AC73: 0 | AD73: 0 | AE73: 0 | AF73: 0 | AG73: 0 | AH73: 0
C74: Other income (expense), net | I74: -17355 | J74: 1831 | K74: -3095 | L74: 19958 | M74: 0 | N74: 0 | O74: 0 | P74: 0 | Q74: 0 | R74: 0 | S74: 0 | T74: 0 | U74: 0 | V74: 0 | W74: 0 | X74: 0 | Y74: 0 | Z74: 0 | AA74: 0 | AB74: 0 | AC74: 0 | AD74: 0 | AE74: 0 | AF74: 0 | AG74: 0 | AH74: 0
C75: Total other income | I75: =SUM(I73:I74) -> -34043 | J75: =SUM(J73:J74) -> 67759 | K75: =SUM(K73:K74) -> 142578 | L75: =SUM(L73:L74) -> 198867 | M75: =SUM(M73:M74) -> 0 | N75: =SUM(N73:N74) -> 0 | O75: =SUM(O73:O74) -> 0 | P75: =SUM(P73:P74) -> 0 | ... AH75: =SUM(AH73:AH74) -> 0
C76: Income before income taxes | I76: =I71+I75 -> 1340954 | J76: =J71+J75 -> 1554328 | K76: =K71+K75 -> 1714601 | L76: =L71+L75 -> 1895581 | M76: =M71+M75 -> 1696714 | N76: =N71+N75 -> 1704221 | O76: =O71+O75 -> 1757072.9 | P76: =P71+P75 -> 1807458.3 | ... AH76: =AH71+AH75 -> 0
C77: Income tax expense | I77: -250824 | J77: -316587 | K77: -352254 | L77: -347218 | M77: =L77 -> -347218 | N77: =N76*N48 -> -332044.42 | O77: =O76*O48 -> -342341.9 | P77: =P76*P48 -> -352158.82 | Q77: =Q76*Q48 -> -361447.79 | R77: =R76*R48 -> -370159.58 | S77: =S76*S48 -> -378243.09 | T77: =T76*T48 -> -385645.27 | U77: =U76*U48 -> -392311.04 | ... AH77: =AH76*AH48 -> 0
C78: Net income | I78: =I76+I77 -> 1090130 | J78: =J76+J77 -> 1237741 | K78: =K76+K77 -> 1362347 | L78: =L76+L77 -> 1548363 | M78: =M76+M77 -> 1349496 | N78: =N76+N77 -> 1372176.6 | O78: =O76+O77 -> 1414731 | P78: =P76+P77 -> 1455299.5 | ... AH78: =AH76+AH77 -> 0
C79: Less: Net income (loss) attributable to redeemable noncontrolling interest | J79: 0 | K79: -673 | L79: -4086 | M79: =L79 -> -4086 | N79: =M79*N10 -> -4086 | O79: =N79*O10 -> -4086 | P79: =O79*P10 -> -4086 | Q79: =P79*Q10 -> -4086 | R79: =Q79*R10 -> -4086 | S79: =R79*S10 -> -4086 | T79: =S79*T10 -> -4086 | U79: =T79*U10 -> -4086 | ... AH79: =AG79*AH10 -> 0
C80: Net income attributable to Copart, Inc. | I80: =I78-I79 -> 1090130 | J80: =J78-J79 -> 1237741 | K80: =K78-K79 -> 1363020 | L80: =L78-L79 -> 1552449 | M80: =M78-M79 -> 1353582 | N80: =N78-N79 -> 1376262.6 | O80: =O78-O79 -> 1418817 | P80: =P78-P79 -> 1459385.5 | ... AH80: =AH78-AH79 -> 0
C82: Basic net income per common share | I82: 4.59 | J82: 1.3 | K82: 1.42 | L82: 1.61 | M82: =M80/M83 -> 1.402231 | N82: =N80/N83 -> 1.4257267 | O82: =O80/O83 -> 1.4698106 | P82: =P80/P83 -> 1.5118372 | Q82: =Q80/Q83 -> 1.5516036 | R82: =R80/R83 -> 1.5888991 | S82: =S80/S83 -> 1.6235049 | T82: =T80/T83 -> 1.6551939 | ... AH82: =AH80/AH83 -> #DIV/0!
C83: Weighted average common shares outstanding | I83: 237419 | J83: 953574 | K83: 960739 | L83: 965306 | M83: =L83 -> 965306 | N83: =M83*N10 -> 965306 | O83: =N83*O10 -> 965306 | P83: =O83*P10 -> 965306 | Q83: =P83*Q10 -> 965306 | R83: =Q83*R10 -> 965306 | S83: =R83*S10 -> 965306 | T83: =S83*T10 -> 965306 | U83: =T83*U10 -> 965306 | ... AH83: =AG83*AH10 -> 0
C85: Diluted net income per common share | I85: 4.52 | J85: 1.28 | K85: 1.4 | L85: 1.59 | M85: =M80/M86 -> 1.3846494 | N85: =N80/N86 -> 1.4078505 | O85: =O80/O86 -> 1.4513816 | P85: =P80/P86 -> 1.4928813 | Q85: =Q80/Q86 -> 1.5321491 | R85: =R80/R86 -> 1.568977 | S85: =S80/S86 -> 1.6031489 | T85: =T80/T86 -> 1.6344405 | ... AH85: =AH80/AH86 -> #DIV/0!
C86: Diluted weighted average common shares outstanding | I86: 241151 | J86: 966647 | K86: 974798 | L86: 977563 | M86: =L86 -> 977563 | N86: =M86*N10 -> 977563 | O86: =N86*O10 -> 977563 | P86: =O86*P10 -> 977563 | Q86: =P86*Q10 -> 977563 | R86: =Q86*R10 -> 977563 | S86: =R86*S10 -> 977563 | T86: =S86*T10 -> 977563 | U86: =T86*U10 -> 977563 | ... AH86: =AG86*AH10 -> 0
C88: Cash Flow Statement
C90: Dep and amort as % of TI | I90: =I97/I65 -> 0.03959101 | J90: =J97/J65 -> 0.041267155 | K90: =K97/K65 -> 0.044905345 | L90: =L97/L65 -> 0.046865928 | M90: =M97/M65 -> 0 | N90: =N97/N65 -> 0.049468495 | O90: =O97/O65 -> 0.051588081 | P90: =P97/P65 -> 0.053282072 | ... W90: =W97/W65 -> 0.056511814 | X90: =W90*X$10 -> 0 | Y90: =X90*Y$10 -> 0 | Z90: =Y90*Z$10 -> 0 | AA90: =Z90*AA$10 -> 0 | AB90: =AA90*AB$10 -> 0 | AC90: =AB90*AC$10 -> 0 | AD90: =AC90*AD$10 -> 0 | AE90: =AD90*AE$10 -> 0 | ... AH90: =AG90*AH$10 -> 0
C91: Capex % of TI | I91: =I117/I65 -> -0.09638835 | J91: =J117/J65 -> -0.1335143 | K91: =K117/K65 -> -0.12060688 | L91: =L117/L65 -> -0.12244354 | M91: =M117/M65 -> 0 | N91: =N117/N65 -> -0.10790568 | O91: =O117/O65 -> -0.099975536 | P91: =P117/P65 -> -0.092592177 | ... W91: =W117/W65 -> -0.049366685 | X91: =W91*X$10 -> 0 | Y91: =X91*Y$10 -> 0 | Z91: =Y91*Z$10 -> 0 | AA91: =Z91*AA$10 -> 0 | AB91: =AA91*AB$10 -> 0 | AC91: =AB91*AC$10 -> 0 | AD91: =AC91*AD$10 -> 0 | AE91: =AD91*AE$10 -> 0 | ... AH91: =AG91*AH$10 -> 0
C92: Capex / Units Sold | I92: =-I117/I24 -> 86.856519 | J92: =-J117/J24 -> 156.80726 | K92: =-K117/K24 -> 133.34325 | L92: =-L117/L24 -> 141.95507 | N92: 130 | O92: =N92-($N$92-$W$92)/10 -> 125 | P92: =O92-($N$92-$W$92)/10 -> 120 | Q92: =P92-($N$92-$W$92)/10 -> 115 | R92: =Q92-($N$92-$W$92)/10 -> 110 | S92: =R92-($N$92-$W$92)/10 -> 105 | T92: =S92-($N$92-$W$92)/10 -> 100 | U92: =T92-($N$92-$W$92)/10 -> 95 | V92: =U92-($N$92-$W$92)/10 -> 90 | W92: 80
C94: Cash flows from operating activities:
C95: Net income | I95: =I78 -> 1090130 | J95: =J78 -> 1237741 | K95: =K78 -> 1362347 | L95: =L78 -> 1548363 | M95: =M78 -> 1349496 | N95: =N78 -> 1372176.6 | O95: =O78 -> 1414731 | P95: =P78 -> 1455299.5 | ... AH95: =AH78 -> 0
C96: Adjustments to reconcile net income to net cash provided by operating activities:
C97: Depreciation and amortization, including debt cost | I97: 138605 | J97: 159684 | K97: 190256 | L97: 217784 | N97: =-PPE!N6 -> 244444.33 | O97: =-PPE!O6 -> 270671.87 | P97: =-PPE!P6 -> 296428.12 | Q97: =-PPE!Q6 -> 321673.59 | R97: =-PPE!R6 -> 346367.77 | S97: =-PPE!S6 -> 370469.13 | T97: =-PPE!T6 -> 393935.06 | U97: =-PPE!U6 -> 416721.9 | ... W97: =-PPE!W6 -> 458825.54 | X97: =X90*X65 -> 0 | Y97: =Y90*Y65 -> 0 | Z97: =Z90*Z65 -> 0 | AA97: =AA90*AA65 -> 0 | AB97: =AB90*AB65 -> 0 | AC97: =AC90*AC65 -> 0 | AD97: =AD90*AD65 -> 0 | AE97: =AE90*AE65 -> 0 | ... AH97: =AH90*AH65 -> 0
C98: Allowance for credit losses | I98: 1349 | J98: 1946 | K98: 3914 | L98: 354 | M98: =SUM(M99:M101) -> 0 | N98: =MAX($I$98:$L$98)*N10 -> 3914 | O98: =MAX($I$98:$L$98)*O10 -> 3914 | P98: =MAX($I$98:$L$98)*P10 -> 3914 | Q98: =MAX($I$98:$L$98)*Q10 -> 3914 | R98: =MAX($I$98:$L$98)*R10 -> 3914 | S98: =MAX($I$98:$L$98)*S10 -> 3914 | T98: =MAX($I$98:$L$98)*T10 -> 3914 | U98: =MAX($I$98:$L$98)*U10 -> 3914 | ... AH98: =MAX($I$98:$L$98)*AH10 -> 0
C99: Gain on extinguishment of liabilities | I99: 0 | J99: 0 | K99: -4058 | L99: 0 | N99: 0 | O99: 0 | P99: 0 | Q99: 0 | R99: 0 | S99: 0 | T99: 0 | U99: 0 | V99: 0 | W99: 0 | X99: 0 | Y99: 0 | Z99: 0 | AA99: 0 | AB99: 0 | AC99: 0 | AD99: 0 | AE99: 0 | AF99: 0 | AG99: 0 | AH99: 0
C100: Equity in (income) losses of unconsolidated affiliates | I100: 284 | J100: 5347 | K100: 2241 | L100: -149 | N100: 0 | O100: 0 | P100: 0 | Q100: 0 | R100: 0 | S100: 0 | T100: 0 | U100: 0 | V100: 0 | W100: 0 | X100: 0 | Y100: 0 | Z100: 0 | AA100: 0 | AB100: 0 | AC100: 0 | AD100: 0 | AE100: 0 | AF100: 0 | AG100: 0 | AH100: 0
C101: Stock-based compensation | I101: 38965 | J101: 39673 | K101: 35234 | L101: 38004 | N101: 0 | O101: 0 | P101: 0 | Q101: 0 | R101: 0 | S101: 0 | T101: 0 | U101: 0 | V101: 0 | W101: 0 | X101: 0 | Y101: 0 | Z101: 0 | AA101: 0 | AB101: 0 | AC101: 0 | AD101: 0 | AE101: 0 | AF101: 0 | AG101: 0 | AH101: 0
C102: Gain on sale of property and equipment | I102: -939 | J102: -1846 | K102: -2386 | L102: -13726 | N102: 0 | O102: 0 | P102: 0 | Q102: 0 | R102: 0 | S102: 0 | T102: 0 | U102: 0 | V102: 0 | W102: 0 | X102: 0 | Y102: 0 | Z102: 0 | AA102: 0 | AB102: 0 | AC102: 0 | AD102: 0 | AE102: 0 | AF102: 0 | AG102: 0 | AH102: 0
C103: Loss on Extinguishble Debt | I103: 16759 | N103: 0 | O103: 0 | P103: 0 | Q103: 0 | R103: 0 | S103: 0 | T103: 0 | U103: 0 | V103: 0 | W103: 0 | X103: 0 | Y103: 0 | Z103: 0 | AA103: 0 | AB103: 0 | AC103: 0 | AD103: 0 | AE103: 0 | AF103: 0 | AG103: 0 | AH103: 0
C104: Deferred income (benefits) taxes | I104: 17017 | J104: 9946 | K104: -847 | L104: -13440 | N104: 0 | O104: 0 | P104: 0 | Q104: 0 | R104: 0 | S104: 0 | T104: 0 | U104: 0 | V104: 0 | W104: 0 | X104: 0 | Y104: 0 | Z104: 0 | AA104: 0 | AB104: 0 | AC104: 0 | AD104: 0 | AE104: 0 | AF104: 0 | AG104: 0 | AH104: 0
C105: Changes in operating assets and liabilities, net of effects from acquisitions:
C106: Accounts receivable | I106: -97750 | J106: -123207 | K106: -145385 | L106: -33950 | N106: =(M156-N156)*N10 -> -65742.943 | O106: =(N156-O156)*O10 -> -53160.755 | P106: =(O156-P156)*P10 -> -55111.748 | Q106: =(P156-Q156)*Q10 -> -57114.119 | R106: =(Q156-R156)*R10 -> -59169.272 | S106: =(R156-S156)*S10 -> -61278.662 | T106: =(S156-T156)*T10 -> -63443.794 | U106: =(T156-U156)*U10 -> -65666.227 | ... AH106: =(AG156-AH156)*AH10 -> 0
C107: Vehicle pooling costs | I107: -18342 | J107: -10989 | K107: -9542 | L107: 16705 | N107: =(M157-N157)*N10 -> -11112.63 | O107: =(N157-O157)*O10 -> -6454.5815 | P107: =(O157-P157)*P10 -> -6777.3106 | Q107: =(P157-Q157)*Q10 -> -7116.1761 | R107: =(Q157-R157)*R10 -> -7471.9849 | S107: =(R157-S157)*S10 -> -7845.5842 | T107: =(S157-T157)*T10 -> -8237.8634 | U107: =(T157-U157)*U10 -> -8649.7565 | ... AH107: =(AG157-AH157)*AH10 -> 0
C108: Inventories | I108: -10851 | J108: 26549 | K108: -3698 | L108: 4655 | N108: =(M158-N158)*N10 -> 3220.0214 | O108: =(N158-O158)*O10 -> -2868.2318 | P108: =(O158-P158)*P10 -> -2973.4955 | Q108: =(P158-Q158)*Q10 -> -3081.5313 | R108: =(Q158-R158)*R10 -> -3192.4149 | S108: =(R158-S158)*S10 -> -3306.2248 | T108: =(S158-T158)*T10 -> -3423.0422 | U108: =(T158-U158)*U10 -> -3542.9511 | ... AH108: =(AG158-AH158)*AH10 -> 0
C109: Prepaid expenses and other current and non-current assets | I109: -5156 | J109: -59949 | K109: -71067 | L109: 7748 | N109: =(M160-N160)*N10 -> 13356.4 | O109: =(N160-O160)*O10 -> -2521.452 | P109: =(O160-P160)*P10 -> -2613.989 | Q109: =(P160-Q160)*Q10 -> -2708.9629 | R109: =(Q160-R160)*R10 -> -2806.4402 | S109: =(R160-S160)*S10 -> -2906.4901 | T109: =(S160-T160)*T10 -> -3009.1838 | U109: =(T160-U160)*U10 -> -3114.5954 | ... AH109: =(AG160-AH160)*AH10 -> 0
C110: Operating lease right-of-use assets and lease liabilities | I110: 715 | J110: 350 | K110: 1064 | L110: 478 | N110: =(M163-N163)*N10 -> 0 | O110: =(N163-O163)*O10 -> 0 | P110: =(O163-P163)*P10 -> 0 | Q110: =(P163-Q163)*Q10 -> 0 | R110: =(Q163-R163)*R10 -> 0 | S110: =(R163-S163)*S10 -> 0 | T110: =(S163-T163)*T10 -> 0 | U110: =(T163-U163)*U10 -> 0 | ... AH110: =(AG163-AH163)*AH10 -> 0
C111: Accounts payable and accrued liabilities | I111: 36306 | J111: 18010 | K111: 59528 | L111: 69599 | N111: =(N170-M170)*N10 -> 23032.516 | O111: =(O170-N170)*O10 -> 48467.645 | P111: =(P170-O170)*P10 -> 51092.077 | Q111: =(Q170-P170)*Q10 -> 53819.848 | R111: =(R170-Q170)*R10 -> 56654.302 | S111: =(S170-R170)*S10 -> 59598.897 | T111: =(T170-S170)*T10 -> 62657.211 | U111: =(U170-T170)*U10 -> 65832.95 | ... AH111: =(AH170-AG170)*AH10 -> 0
C112: Deferred revenue | I112: -574 | J112: 5896 | K112: 1867 | L112: 2159 | N112: 0 | O112: 0 | P112: 0 | Q112: 0 | R112: 0 | S112: 0 | T112: 0 | U112: 0 | V112: 0 | W112: 0 | X112: 0 | Y112: 0 | Z112: 0 | AA112: 0 | AB112: 0 | AC112: 0 | AD112: 0 | AE112: 0 | AF112: 0 | AG112: 0 | AH112: 0
C113: Income taxes receivable | I113: -29884 | J113: 33193 | K113: 6561 | L113: -575 | N113: 0 | O113: 0 | P113: 0 | Q113: 0 | R113: 0 | S113: 0 | T113: 0 | U113: 0 | V113: 0 | W113: 0 | X113: 0 | Y113: 0 | Z113: 0 | AA113: 0 | AB113: 0 | AC113: 0 | AD113: 0 | AE113: 0 | AF113: 0 | AG113: 0 | AH113: 0
C114: Income taxes payable | I114: 49 | J114: 21866 | K114: 46535 | L114: -44259 | N114: 0 | O114: 0 | P114: 0 | Q114: 0 | R114: 0 | S114: 0 | T114: 0 | U114: 0 | V114: 0 | W114: 0 | X114: 0 | Y114: 0 | Z114: 0 | AA114: 0 | AB114: 0 | AC114: 0 | AD114: 0 | AE114: 0 | AF114: 0 | AG114: 0 | AH114: 0
C115: Net cash provided by operating activities | I115: =SUM(I95:I114) -> 1176683 | J115: =SUM(J95:J114) -> 1364210 | K115: =SUM(K95:K114) -> 1472564 | L115: =SUM(L95:L114) -> 1799750 | M115: =SUM(M95:M114) -> 1349496 | N115: =SUM(N95:N114) -> 1583288.3 | O115: =SUM(O95:O114) -> 1672779.5 | P115: =SUM(P95:P114) -> 1739257.2 | ... AH115: =SUM(AH95:AH114) -> 0
C116: Cash flows from investing activities:
C117: Purchases of property and equipment | I117: -337448 | J117: -516636 | K117: -510990 | L117: -568990 | N117: =-N92*N24 -> -533206.67 | O117: =-O92*O24 -> -524550.72 | P117: =-P92*P24 -> -515124.95 | Q117: =-Q92*Q24 -> -504909.39 | R117: =-R92*R24 -> -493883.71 | S117: =-S92*S24 -> -482027.17 | T117: =-T92*T24 -> -469318.67 | U117: =-U92*U24 -> -455736.7 | ... W117: =-W92*W24 -> -400813.46 | X117: =X91*X65 -> 0 | Y117: =Y91*Y65 -> 0 | Z117: =Z91*Z65 -> 0 | AA117: =AA91*AA65 -> 0 | AB117: =AB91*AB65 -> 0 | AC117: =AC91*AC65 -> 0 | AD117: =AD91*AD65 -> 0 | AE117: =AE91*AE65 -> 0 | ... AH117: =AH91*AH65 -> 0
C118: Assets and liabilities acquired in connection with acquisition | I118: -106604 | J118: 0 | K118: 17662 | L118: -1223 | N118: 0 | O118: 0 | P118: 0 | Q118: 0 | R118: 0 | S118: 0 | T118: 0 | U118: 0 | V118: 0 | W118: 0 | X118: 0 | Y118: 0 | Z118: 0 | AA118: 0 | AB118: 0 | AC118: 0 | AD118: 0 | AE118: 0 | AF118: 0 | AG118: 0 | AH118: 0
...

Sheet DCF
C2: Discounted CashFlow
D3: Period Labels | I3: =YEAR('Operating Model'!I9) -> 2022 | J3: =YEAR('Operating Model'!J9) -> 2023 | K3: =YEAR('Operating Model'!K9) -> 2024 | L3: =YEAR('Operating Model'!L9) -> 2025 | M3: =YEAR('Operating Model'!M9) -> 2025 | N3: =YEAR('Operating Model'!N9) -> 2026 | O3: =YEAR('Operating Model'!O9) -> 2027 | P3: =YEAR('Operating Model'!P9) -> 2028 | ... AH3: =YEAR('Operating Model'!AH9) -> 2046
D4: Forecast | I4: ='Operating Model'!I10 -> FALSE | J4: ='Operating Model'!J10 -> FALSE | K4: ='Operating Model'!K10 -> FALSE | L4: ='Operating Model'!L10 -> FALSE | M4: ='Operating Model'!M10 -> FALSE | N4: ='Operating Model'!N10 -> TRUE | O4: ='Operating Model'!O10 -> TRUE | P4: ='Operating Model'!P10 -> TRUE | ... AH4: ='Operating Model'!AH10 -> FALSE
D5: Forecast Periods | I5: =(H5+I4)*I4 -> 0 | J5: =(I5+J4)*J4 -> 0 | K5: =(J5+K4)*K4 -> 0 | L5: =(K5+L4)*L4 -> 0 | M5: =(L5+M4)*M4 -> 0 | N5: =(M5+N4)*N4 -> 1 | O5: =(N5+O4)*O4 -> 2 | P5: =(O5+P4)*P4 -> 3 | ... AH5: =(AG5+AH4)*AH4 -> 0
D6: Mid Year Discount Periods | I6: =(H5+0.5)*I4 -> 0 | J6: =(I5+0.5)*J4 -> 0 | K6: =(J5+0.5)*K4 -> 0 | L6: =(K5+0.5)*L4 -> 0 | M6: =(L5+0.5)*M4 -> 0 | N6: =(M5+0.5)*N4 -> 0.5 | O6: =(N5+0.5)*O4 -> 1.5 | P6: =(O5+0.5)*P4 -> 2.5 | ... AH6: =(AG5+0.5)*AH4 -> 0
C8: WACC | G8: =WACC!F34 -> 0.078425824 | I8: Intrinsic Value Per Share | L8: =G44 -> 39.026671
C9: PGR | G9: 0.04 | I9: Current Price | L9: =G45 -> 28.91
C10: Scaler | G10: 0.06
C12: Tax Rates | I12: ='Operating Model'!I48*I4 -> 0 | J12: ='Operating Model'!J48*J4 -> 0 | K12: ='Operating Model'!K48*K4 -> 0 | L12: ='Operating Model'!L48*L4 -> 0 | M12: ='Operating Model'!M48*M4 -> 0 | N12: ='Operating Model'!N48*N4 -> -0.19483648 | O12: ='Operating Model'!O48*O4 -> -0.19483648 | P12: ='Operating Model'!P48*P4 -> -0.19483648 | ... AH12: ='Operating Model'!AH48*AH4 -> 0
C14: EBIT | I14: ='Operating Model'!I71*I4 -> 0 | J14: ='Operating Model'!J71*J4 -> 0 | K14: ='Operating Model'!K71*K4 -> 0 | L14: ='Operating Model'!L71*L4 -> 0 | M14: ='Operating Model'!M71*M4 -> 0 | N14: ='Operating Model'!N71*N4 -> 1704221 | O14: ='Operating Model'!O71*O4 -> 1757072.9 | P14: ='Operating Model'!P71*P4 -> 1807458.3 | ... AH14: ='Operating Model'!AH71*AH4 -> 0
C15: Tax | I15: =I12*I14 -> 0 | J15: =J12*J14 -> 0 | K15: =K12*K14 -> 0 | L15: =L12*L14 -> 0 | M15: =M12*M14 -> 0 | N15: =N12*N14 -> -332044.42 | O15: =O12*O14 -> -342341.9 | P15: =P12*P14 -> -352158.82 | ... AH15: =AH12*AH14 -> 0
C16: NOPAT | I16: =I14+I15 -> 0 | J16: =J14+J15 -> 0 | K16: =K14+K15 -> 0 | L16: =L14+L15 -> 0 | M16: =M14+M15 -> 0 | N16: =N14+N15 -> 1372176.6 | O16: =O14+O15 -> 1414731 | P16: =P14+P15 -> 1455299.5 | ... AH16: =AH14+AH15 -> 0
C17: Depreciation | I17: =-PPE!I6*I4 -> 0 | J17: =-PPE!J6*J4 -> 0 | K17: =-PPE!K6*K4 -> 0 | L17: =-PPE!L6*L4 -> 0 | M17: =-PPE!M6*M4 -> 0 | N17: =-PPE!N6*N4 -> 244444.33 | O17: =-PPE!O6*O4 -> 270671.87 | P17: =-PPE!P6*P4 -> 296428.12 | ... AH17: =-PPE!AH6*AH4 -> 0
C18: Capex | I18: ='Operating Model'!I117*I4 -> 0 | J18: ='Operating Model'!J117*J4 -> 0 | K18: ='Operating Model'!K117*K4 -> 0 | L18: ='Operating Model'!L117*L4 -> 0 | M18: ='Operating Model'!M117*M4 -> 0 | N18: ='Operating Model'!N117*N4 -> -533206.67 | O18: ='Operating Model'!O117*O4 -> -524550.72 | P18: ='Operating Model'!P117*P4 -> -515124.95 | ... AH18: ='Operating Model'!AH117*AH4 -> 0
C19: Change in Net working capital | I19: =SUM('Operating Model'!I106:I114)*DCF!I4 -> 0 | J19: =SUM('Operating Model'!J106:J114)*DCF!J4 -> 0 | K19: =SUM('Operating Model'!K106:K114)*DCF!K4 -> 0 | L19: =SUM('Operating Model'!L106:L114)*DCF!L4 -> 0 | M19: =SUM('Operating Model'!M106:M114)*DCF!M4 -> 0 | N19: =SUM('Operating Model'!N106:N114)*DCF!N4 -> -37246.636 | O19: =SUM('Operating Model'!O106:O114)*DCF!O4 -> -16537.376 | P19: =SUM('Operating Model'!P106:P114)*DCF!P4 -> -16384.467 | ... AH19: =SUM('Operating Model'!AH106:AH114)*DCF!AH4 -> 0
C20: Unlevered Free Cash Flow | I20: =SUM(I16:I19) -> 0 | J20: =SUM(J16:J19) -> 0 | K20: =SUM(K16:K19) -> 0 | L20: =SUM(L16:L19) -> 0 | M20: =SUM(M16:M19) -> 0 | N20: =SUM(N16:N19) -> 1046167.6 | O20: =SUM(O16:O19) -> 1144314.8 | P20: =SUM(P16:P19) -> 1220218.2 | ... AH20: =SUM(AH16:AH19) -> 0
D21: % growth | J21: =IFERROR(J20/I20-1,0)*J4 -> 0 | K21: =IFERROR(K20/J20-1,0)*K4 -> 0 | L21: =IFERROR(L20/K20-1,0)*L4 -> 0 | M21: =IFERROR(M20/L20-1,0)*M4 -> 0 | N21: =IFERROR(N20/M20-1,0)*N4 -> 0 | O21: =IFERROR(O20/N20-1,0)*O4 -> 0.093815917 | P21: =IFERROR(P20/O20-1,0)*P4 -> 0.066330926 | Q21: =IFERROR(Q20/P20-1,0)*Q4 -> 0.060670544 | ... AH21: =IFERROR(AH20/AG20-1,0)*AH4 -> 0
C22: Discounting Factor | I22: =(1/(1+$G$8)^I6)*I4 -> 0 | J22: =(1/(1+$G$8)^J6)*J4 -> 0 | K22: =(1/(1+$G$8)^K6)*K4 -> 0 | L22: =(1/(1+$G$8)^L6)*L4 -> 0 | M22: =(1/(1+$G$8)^M6)*M4 -> 0 | N22: =(1/(1+$G$8)^N6)*N4 -> 0.96295249 | O22: =(1/(1+$G$8)^O6)*O4 -> 0.89292418 | P22: =(1/(1+$G$8)^P6)*P4 -> 0.8279885 | ... AH22: =(1/(1+$G$8)^AH6)*AH4 -> 0
C23: Discounted Free Cash Flow | I23: =I20*I22 -> 0 | J23: =J20*J22 -> 0 | K23: =K20*K22 -> 0 | L23: =L20*L22 -> 0 | M23: =M20*M22 -> 0 | N23: =N20*N22 -> 1007409.7 | O23: =O20*O22 -> 1021786.3 | P23: =P20*P22 -> 1010326.6 | ... AH23: =AH20*AH22 -> 0
D25: NOPAT growth | J25: =IFERROR(J16/I16-1,0)*J4 -> 0 | K25: =IFERROR(K16/J16-1,0)*K4 -> 0 | L25: =IFERROR(L16/K16-1,0)*L4 -> 0 | M25: =IFERROR(M16/L16-1,0)*M4 -> 0 | N25: =IFERROR(N16/M16-1,0)*N4 -> 0 | O25: =IFERROR(O16/N16-1,0)*O4 -> 0.031012352 | P25: =IFERROR(P16/O16-1,0)*P4 -> 0.02867579 | Q25: =IFERROR(Q16/P16-1,0)*Q4 -> 0.026377216 | ... AH25: =IFERROR(AH16/AG16-1,0)*AH4 -> 0
D26: Capex Growth | J26: =IFERROR(J18/I18-1,0)*J4 -> 0 | K26: =IFERROR(K18/J18-1,0)*K4 -> 0 | L26: =IFERROR(L18/K18-1,0)*L4 -> 0 | M26: =IFERROR(M18/L18-1,0)*M4 -> 0 | N26: =IFERROR(N18/M18-1,0)*N4 -> 0 | O26: =IFERROR(O18/N18-1,0)*O4 -> -0.016233766 | P26: =IFERROR(P18/O18-1,0)*P4 -> -0.017969231 | Q26: =IFERROR(Q18/P18-1,0)*Q4 -> -0.019831224 | ... AH26: =IFERROR(AH18/AG18-1,0)*AH4 -> 0
D27: Invested Capital | I27: =('Operating Model'!I188+'Operating Model'!I181+'Operating Model'!I177+'Operating Model'!I178-'Operating Model'!I154-'Operating Model'!I155)*I4 -> 0 | J27: =('Operating Model'!J188+'Operating Model'!J181+'Operating Model'!J177+'Operating Model'!J178-'Operating Model'!J154-'Operating Model'!J155)*J4 -> 0 | K27: =('Operating Model'!K188+'Operating Model'!K181+'Operating Model'!K177+'Operating Model'!K178-'Operating Model'!K154-'Operating Model'!K155)*K4 -> 0 | L27: =('Operating Model'!L188+'Operating Model'!L181+'Operating Model'!L177+'Operating Model'!L178-'Operating Model'!L154-'Operating Model'!L155)*L4 -> 0 | M27: =('Operating Model'!M188+'Operating Model'!M181+'Operating Model'!M177+'Operating Model'!M178-'Operating Model'!M154-'Operating Model'!M155)*M4 -> 0 | N27: =('Operating Model'!N188+'Operating Model'!N181+'Operating Model'!N177+'Operating Model'!N178-'Operating Model'!N154-'Operating Model'!N155)*N4 -> 4995033 | O27: =('Operating Model'!O188+'Operating Model'!O181+'Operating Model'!O177+'Operating Model'!O178-'Operating Model'!O154-'Operating Model'!O155)*O4 -> 5265449.2 | P27: =('Operating Model'!P188+'Operating Model'!P181+'Operating Model'!P177+'Operating Model'!P178-'Operating Model'!P154-'Operating Model'!P155)*P4 -> 5500530.5 | ... AH27: =('Operating Model'!AH188+'Operating Model'!AH181+'Operating Model'!AH177+'Operating Model'!AH178-'Operating Model'!AH154-'Operating Model'!AH155)*AH4 -> 0
D28: ROIC | I28: =IFERROR(I16/I27,0) -> 0 | J28: =IFERROR(J16/J27,0) -> 0 | K28: =IFERROR(K16/K27,0) -> 0 | L28: =IFERROR(L16/L27,0) -> 0 | M28: =IFERROR(M16/M27,0) -> 0 | N28: =IFERROR(N16/N27,0) -> 0.27470821 | O28: =IFERROR(O16/O27,0) -> 0.26868192 | P28: =IFERROR(P16/P27,0) -> 0.26457439 | ... AH28: =IFERROR(AH16/AH27,0) -> 0
D30: NOPAT CAGR | G30: =(W16/N16)^(1/9)-1 -> 0.021808904
D31: Capex CAGR | G31: =(W18/N18)^(1/9)-1 -> -0.031214982
D32: Unlevered FCF CAGR | G32: =(W20/N20)^(1/9)-1 -> 0.056103108
C34: Terminal Value | G34: =W20*(1+G9)/(G8-G9) -> 46277331
D35: Discounted Terminal Value | G35: =G34*W22 -> 22587109 | H35: =G35/$G$37 -> 0.70492361
C36: Dicounted FCF | G36: =SUM(I23:AH23) -> 9454815.7 | H36: =G36/$G$37 -> 0.29507639
C37: Enterprise Value | G37: =G35+G36 -> 32041925 | H37: =G37/$G$37 -> 1
C38: Cash | G38: ='Operating Model'!M154 -> 3354142
C39: ='Operating Model'!C155 -> Investment in held to maturity securities | G39: ='Operating Model'!M155 -> 845570
C40: Debt + leases | G40: =-'Operating Model'!M178-'Operating Model'!M177-'Operating Model'!M173 -> -93116
C41: Redeeemable Non-Controlling Interest | G41: =-'Operating Model'!M181 -> -17181
C42: Equity Value | G42: =SUM(G37:G41) -> 36131340
C43: Share Count | G43: =WACC!F5 -> 925811.48
C44: Intrinsic Value Per Share | G44: =G42/G43 -> 39.026671
C45: Current Price | G45: =WACC!F4 -> 28.91
C46: Valuation % | G46: =G44/G45-1 -> 0.34993672
G48: Intrinsic Values | M48: WACC
H49: =G44 -> 39.026671 | I49: 0.064561466 | J49: =I49+0.5% -> 0.069561466 | K49: =J49+0.5% -> 0.074561466 | L49: =K49+0.5% -> 0.079561466 | M49: =L49+0.5% -> 0.084561466 | N49: =M49+0.5% -> 0.089561466 | O49: =N49+0.5% -> 0.094561466 | P49: =O49+0.5% -> 0.099561466 | Q49: =P49+0.5% -> 0.10456147
H50: 0.02 | I50: 38.625144 | J50: 35.111164 | K50: 32.24429 | L50: 29.861445 | M50: 27.850075 | N50: 26.129988 | O50: 24.642511 | P50: 23.343718 | Q50: 22.200078
H51: =H50+0.5% -> 0.025 | I51: 41.702817 | J51: 37.471931 | K51: 34.097436 | L51: 31.343798 | M51: 29.054573 | N51: 27.121788 | O51: 25.468513 | P51: 24.038458 | Q51: 22.789486
G52: PGR | H52: =H51+0.5% -> 0.03 | I52: 45.670982 | J52: 40.429432 | K52: 36.366445 | L52: 33.125244 | M52: 30.479832 | N52: 28.280104 | O52: 26.422455 | P52: 24.833073 | Q52: 23.457945
H53: =H52+0.5% -> 0.035 | I53: 50.981491 | J53: 44.242655 | K53: 39.208995 | L53: 35.306463 | M53: 32.192665 | N53: 29.650715 | O53: 27.536558 | P53: 25.750766 | Q53: 24.222499
H54: =H53+0.5% -> 0.04 | I54: 58.454131 | J54: 49.345808 | K54: 42.874006 | L54: 38.039032 | M54: 34.289873 | N54: 31.297875 | O54: 28.854854 | P54: 26.822535 | Q54: 25.105476
H55: =H54+0.5% -> 0.045 | I55: 69.746852 | J55: 56.526668 | K55: 47.778811 | L55: 41.562241 | M55: 36.917195 | N55: 33.314672 | O55: 30.439142 | P55: 28.090736 | Q55: 26.1367
H56: =H55+0.5% -> 0.05 | I56: 88.794782 | J56: 67.37845 | K56: 54.680567 | L56: 46.277274 | M56: 40.304705 | N56: 35.841257 | O56: 32.378959 | P56: 29.614823 | Q56: 27.356925
G59: Intrinsic Values | M59: WACC
H60: =G44 -> 39.026671 | I60: 0.064561466 | J60: =I60+0.5% -> 0.069561466 | K60: =J60+0.5% -> 0.074561466 | L60: =K60+0.5% -> 0.079561466 | M60: =L60+0.5% -> 0.084561466 | N60: =M60+0.5% -> 0.089561466 | O60: =N60+0.5% -> 0.094561466 | P60: =O60+0.5% -> 0.099561466 | Q60: =P60+0.5% -> 0.10456147
H61: 0.05 | I61: 51.882721 | J61: 43.90526 | K61: 38.236585 | L61: 34.001284 | M61: 30.716844 | N61: 28.095467 | O61: 25.954851 | P61: 24.173907 | Q61: 22.669061
H62: =H61+0.5% -> 0.055 | I62: 55.168426 | J62: 46.625534 | K62: 40.555296 | L62: 36.020158 | M62: 32.503359 | N62: 29.696671 | O62: 27.404852 | P62: 25.498221 | Q62: 23.887269
G63: SCALER | H63: =H62+0.5% -> 0.06 | I63: 58.454131 | J63: 49.345808 | K63: 42.874006 | L63: 38.039032 | M63: 34.289873 | N63: 31.297875 | O63: 28.854854 | P63: 26.822535 | Q63: 25.105476
H64: =H63+0.5% -> 0.065 | I64: 61.739835 | J64: 52.066082 | K64: 45.192717 | L64: 40.057906 | M64: 36.076388 | N64: 32.899079 | O64: 30.304856 | P64: 28.146848 | Q64: 26.323684
H65: =H64+0.5% -> 0.07 | I65: 65.02554 | J65: 54.786356 | K65: 47.511427 | L65: 42.07678 | M65: 37.862902 | N65: 34.500283 | O65: 31.754858 | P65: 29.471162 | Q65: 27.541891
H66: =H65+0.5% -> 0.075 | I66: 68.311245 | J66: 57.50663 | K66: 49.830138 | L66: 44.095654 | M66: 39.649417 | N66: 36.101486 | O66: 33.204859 | P66: 30.795476 | Q66: 28.760099
H67: =H66+0.5% -> 0.08 | I67: 71.59695 | J67: 60.226904 | K67: 52.148848 | L67: 46.114528 | M67: 41.435931 | N67: 37.70269 | O67: 34.654861 | P67: 32.119789 | Q67: 29.978306

Sheet WACC
C2: WACC Calculations
E4: Share Price | F4: 28.91 | K4: Interest coverage | L4: Spread
E5: Share Count | F5: =925811.482 -> 925811.48 | K5: >8.5 | L5: 0.004
E6: Equity Value | F6: =F4*F5 -> 26765210 | K6: 6.50 - 8.50 | L6: 0.0055
E7: =DCF!C38 -> Cash | F7: =-DCF!G38 -> -3354142 | K7: 5.50 - 6.49 | L7: 0.007
E8: =DCF!C39 -> Investment in held to maturity securities | F8: =-DCF!G39 -> -845570 | K8: 4.25 - 5.49 | L8: 0.0078
E9: =DCF!C40 -> Debt + leases | F9: =-DCF!G40 -> 93116 | K9: 3.00 - 4.24 | L9: 0.0089
E10: =DCF!C41 -> Redeeemable Non-Controlling Interest | F10: =-DCF!G41 -> 17181 | K10: 2.50 - 2.99 | L10: 0.0111
E11: Enterprise Debt | F11: =SUM(F6:F10) -> 22675795 | K11: 2.25 - 2.49 | L11: 0.0138
K12: 2.00 - 2.24 | L12: 0.0184
E13: Ten Year Bond Yield | F13: 0.04643 | K13: 1.75 - 1.99 | L13: 0.0275
E14: Damodaran's US Default Spread | F14: 0.0023 | K14: 1.50 - 1.74 | L14: 0.0321
E15: Risk Free Rate | F15: =F13-F14 -> 0.04413 | K15: 1.25 - 1.49 | L15: 0.0509
K16: 0.80 - 1.24 | L16: 0.0885
E17: Lambda | F17: 1 | K17: 0.65 - 0.79 | L17: 0.1261
E18: Country Risk Premium | F18: 0.0023 | K18: 0.20 - 0.64 | L18: 0.16
E19: Mature Market ERP | F19: 0.0423 | K19: <0.2 | L19: 0.19
E20: Total ERP | F20: =F19+(F17*F18) -> 0.0446
K21: EBIT | L21: ='Operating Model'!L71 -> 1696714
E22: Debt to Equity | F22: =F9/F6 -> 0.0034789938 | K22: Interest Expense | L22: ='Operating Model'!L139 -> 2019
E23: Unlevered Average Beta | F23: =AVERAGE(M39:M59) -> 0.6832841 | K23: EBIT/Interest | L23: =L21/L22 -> 840.37345
E24: Damodaran's Unlevered Beta (Business and Consumer Services) | F24: 0.77
E26: useDamodaranBeta - True, False | F26: TRUE | K26: Company Default Spread | L26: =L5 -> 0.004
E27: Current Beta | F27: =IF(F26,F24,F23) -> 0.77
E28: Tax Rate | F28: 0.21
E29: Levered Beta | F29: =F27*(1+(1-F28)*F22) -> 0.77211627
E31: Cost of Equity | F31: =F15+F29*(F20) -> 0.078566386
E32: Cost of Debt | F32: =F15+L26 -> 0.04813
E34: WACC | F34: =F31*(F6/(F6+F9))+F32*(F9/(F6+F9)*(1-F28)) -> 0.078425824
C37: Beta Array
D38: Ticker | E38: Company | F38: Market Cap | G38: Total Debt | H38: Debt to Equity | I38: Beta | J38: Country | K38: Industry | L38: Corporate Tax Rate | M38: Unlevered Beta
D39: CVNA | E39: Carvana Co. | F39: 102468657152 | G39: 5696999936 | H39: =G39/F39 -> 0.055597488 | I39: 3.488 | J39: United States | K39: Auto & Truck Dealerships | L39: 0.21 | M39: =I39/(1+(1-L39)*H39) -> 3.3412458
D40: 3153.T | E40: Yashima Denki Co., Ltd. | F40: 64063557632 | G40: 700000000 | H40: =G40/F40 -> 0.010926649 | I40: 0.611 | J40: Japan | K40: Industrial Distribution | L40: 0.3 | M40: =I40/(1+(1-L40)*H40) -> 0.60636215
D41: EBAY | E41: eBay Inc. | F41: 48435957760 | G41: 7206000128 | H41: =G41/F41 -> 0.14877377 | I41: 1.355 | J41: United States | K41: Internet Retail | L41: 0.21 | M41: =I41/(1+(1-L41)*H41) -> 1.212494
D42: RBA | E42: RB Global, Inc. | F42: 20724011008 | G42: 4440399872 | H42: =G42/F42 -> 0.21426354 | I42: 0.552 | J42: United States | K42: Specialty Business Services | L42: 0.21 | M42: =I42/(1+(1-L42)*H42) -> 0.47209015
D43: PAG | E43: Penske Automotive Group, Inc. | F43: 14256066560 | G43: 9371199488 | H43: =G43/F43 -> 0.65734819 | I43: 0.833 | J43: United States | K43: Auto & Truck Dealerships | L43: 0.21 | M43: =I43/(1+(1-L43)*H43) -> 0.54827698
D44: 0881.HK | E44: Zhongsheng Group Holdings Limited | F44: 10639637504 | G44: 34658426880 | H44: =G44/F44 -> 3.2574819 | I44: 0.893 | J44: China | K44: Auto & Truck Dealerships | L44: 0.25 | M44: =I44/(1+(1-L44)*H44) -> 0.25935844
D45: AN | E45: AutoNation, Inc. | F45: 7004923904 | G45: 11331300352 | H45: =G45/F45 -> 1.6176193 | I45: 0.727 | J45: United States | K45: Auto & Truck Dealerships | L45: 0.21 | M45: =I45/(1+(1-L45)*H45) -> 0.31915091
D46: AUTO.L | E46: Autotrader Group plc | F46: 4180527616 | G46: 211000000 | H46: =G46/F46 -> 0.050472098 | I46: 0.693 | J46: United Kingdom | K46: Internet Content & Information | L46: 0.25 | M46: =I46/(1+(1-L46)*H46) -> 0.66772393
D47: ABG | E47: Asbury Automotive Group, Inc. | F47: 4005072640 | G47: 5530500096 | H47: =G47/F47 -> 1.3808739 | I47: 0.724 | J47: United States | K47: Auto & Truck Dealerships | L47: 0.21 | M47: =I47/(1+(1-L47)*H47) -> 0.34626397
D48: GPI | E48: Group 1 Automotive, Inc. | F48: 3416313344 | G48: 5611899904 | H48: =G48/F48 -> 1.6426772 | I48: 0.834 | J48: United States | K48: Auto & Truck Dealerships | L48: 0.21 | M48: =I48/(1+(1-L48)*H48) -> 0.3629693
D49: CARG | E49: CarGurus, Inc. | F49: 3409974272 | G49: 187995008 | H49: =G49/F49 -> 0.055130917 | I49: 1.166 | J49: United States | K49: Auto & Truck Dealerships | L49: 0.21 | M49: =I49/(1+(1-L49)*H49) -> 1.1173362
D50: SIX2.DE | E50: Sixt SE | F50: 3302465280 | G50: 3426648064 | H50: =G50/F50 -> 1.0376031 | I50: 1.006 | J50: Germany | K50: Rental & Leasing Services | L50: 0.3 | M50: =I50/(1+(1-L50)*H50) -> 0.58274176
... D59: SAH | E59: Sonic Automotive | F59: 2741477376 | G59: 4671799808 | H59: =G59/F59 -> 1.7041176 | I59: 0.888 | J59: United States | K59: Auto & Truck Dealerships | L59: 0.21 | M59: =I59/(1+(1-L59)*H59) -> 0.37847583

Sheet PPE
D2: PPE and Depreciation | E2: Units | F2: Constants | G2: Constants | I2: 2022 | J2: 2023 | K2: 2024 | L2: 2025 | M2: 2025 | N2: 2026 | O2: 2027 | P2: 2028 | Q2: 2029 | R2: 2030 | S2: 2031 | T2: 2032 | U2: 2033 | V2: 2034 | W2: 2035 | X2: 2036 | Y2: 2037 | Z2: 2038 | AA2: 2039 | AB2: 2040 | AC2: 2041 | AD2: 2042 | AE2: 2043 | AF2: 2044 | AG2: 2045 | AH2: 2046
D3: Forecast Flag | I3: =DCF!I4 -> FALSE | J3: =DCF!J4 -> FALSE | K3: =DCF!K4 -> FALSE | L3: =DCF!L4 -> FALSE | M3: =DCF!M4 -> FALSE | N3: =DCF!N4 -> TRUE | O3: =DCF!O4 -> TRUE | P3: =DCF!P4 -> TRUE | ... AH3: =DCF!AH4 -> FALSE
D4: Beginning PPE | J4: =I7 -> 2485764 | K4: =J7 -> 2844339 | L4: =K7 -> 3175838 | M4: =L7 -> 3598093 | N4: =M7 -> 3598093 | O4: =N7 -> 3886855.3 | P4: =O7 -> 4140734.2 | Q4: =P7 -> 4359431 | ... AH4: =AG7 -> 4860601.6
D5: Capex | I5: =-'Operating Model'!I117 -> 337448 | J5: =-'Operating Model'!J117 -> 516636 | K5: =-'Operating Model'!K117 -> 510990 | L5: =-'Operating Model'!L117 -> 568990 | M5: =-'Operating Model'!M117 -> 0 | N5: =-'Operating Model'!N117 -> 533206.67 | O5: =-'Operating Model'!O117 -> 524550.72 | P5: =-'Operating Model'!P117 -> 515124.95 | ... AH5: =-'Operating Model'!AH117 -> 0
D6: Depreciation | I6: =-'Operating Model'!I97 -> -138605 | J6: =-'Operating Model'!J97 -> -159684 | K6: =-'Operating Model'!K97 -> -190256 | L6: =-'Operating Model'!L97 -> -217784 | M6: =-'Operating Model'!M97 -> 0 | N6: =-N24 -> -244444.33 | O6: =-O24 -> -270671.87 | P6: =-P24 -> -296428.12 | Q6: =-Q24 -> -321673.59 | R6: =-R24 -> -346367.77 | S6: =-S24 -> -370469.13 | T6: =-T24 -> -393935.06 | U6: =-U24 -> -416721.9 | ... AH6: =-AH24 -> 0
D7: Ending PPE | I7: ='Operating Model'!I162 -> 2485764 | J7: ='Operating Model'!J162 -> 2844339 | K7: ='Operating Model'!K162 -> 3175838 | L7: ='Operating Model'!L162 -> 3598093 | M7: =SUM(M4:M6) -> 3598093 | N7: =SUM(N4:N6) -> 3886855.3 | O7: =SUM(O4:O6) -> 4140734.2 | P7: =SUM(P4:P6) -> 4359431 | Q7: =SUM(Q4:Q6) -> 4542666.8 | R7: =SUM(R4:R6) -> 4690182.8 | S7: =SUM(S4:S6) -> 4801740.8 | T7: =SUM(T4:T6) -> 4877124.4 | ... AH7: =SUM(AH4:AH6) -> 4860601.6
D10: Existing PPE Depreciation Period | E10: Years | G10: =-L7/L6 -> 16.521384
D11: Capex average Depreciation Period | E11: Years | G11: 20
D13: Existing PPE Depreciation | G13: =M7/G10 -> 217784 | N13: =G13 -> 217784 | O13: =MAX(0,MIN($N$13,$M$7-SUM($N$13:N13)))*O3 -> 217784 | P13: =MAX(0,MIN($N$13,$M$7-SUM($N$13:O13)))*P3 -> 217784 | Q13: =MAX(0,MIN($N$13,$M$7-SUM($N$13:P13)))*Q3 -> 217784 | R13: =MAX(0,MIN($N$13,$M$7-SUM($N$13:Q13)))*R3 -> 217784 | S13: =MAX(0,MIN($N$13,$M$7-SUM($N$13:R13)))*S3 -> 217784 | T13: =MAX(0,MIN($N$13,$M$7-SUM($N$13:S13)))*T3 -> 217784 | U13: =MAX(0,MIN($N$13,$M$7-SUM($N$13:T13)))*U3 -> 217784 | V13: =MAX(0,MIN($N$13,$M$7-SUM($N$13:U13)))*V3 -> 217784 | ... AH13: =MAX(0,MIN($N$13,$M$7-SUM($N$13:AG13)))*AH3 -> 0
D14: 2026 | F14: {=TRANSPOSE(N5:W5)} -> 533206.67 | G14: =F14/$G$11 -> 26660.334 | N14: =G14 -> 26660.334 | O14: =MAX(0,MIN($N$14,$F$14-SUM($N$14:N14)))*O3 -> 26660.334 | P14: =MAX(0,MIN($N$14,$F$14-SUM($N$14:O14)))*P3 -> 26660.334 | Q14: =MAX(0,MIN($N$14,$F$14-SUM($N$14:P14)))*Q3 -> 26660.334 | R14: =MAX(0,MIN($N$14,$F$14-SUM($N$14:Q14)))*R3 -> 26660.334 | S14: =MAX(0,MIN($N$14,$F$14-SUM($N$14:R14)))*S3 -> 26660.334 | T14: =MAX(0,MIN($N$14,$F$14-SUM($N$14:S14)))*T3 -> 26660.334 | U14: =MAX(0,MIN($N$14,$F$14-SUM($N$14:T14)))*U3 -> 26660.334 | V14: =MAX(0,MIN($N$14,$F$14-SUM($N$14:U14)))*V3 -> 26660.334 | ... AH14: =MAX(0,MIN($N$14,$F$14-SUM($N$14:AG14)))*AH3 -> 0
D15: =D14+1 -> 2027 | F15: 524550.72 | G15: =F15/$G$11 -> 26227.536 | O15: =G15 -> 26227.536 | P15: =MAX(0,MIN($O$15,$F$15-SUM($O$15:O15)))*P3 -> 26227.536 | Q15: =MAX(0,MIN($O$15,$F$15-SUM($O$15:P15)))*Q3 -> 26227.536 | R15: =MAX(0,MIN($O$15,$F$15-SUM($O$15:Q15)))*R3 -> 26227.536 | S15: =MAX(0,MIN($O$15,$F$15-SUM($O$15:R15)))*S3 -> 26227.536 | T15: =MAX(0,MIN($O$15,$F$15-SUM($O$15:S15)))*T3 -> 26227.536 | U15: =MAX(0,MIN($O$15,$F$15-SUM($O$15:T15)))*U3 -> 26227.536 | V15: =MAX(0,MIN($O$15,$F$15-SUM($O$15:U15)))*V3 -> 26227.536 | W15: =MAX(0,MIN($O$15,$F$15-SUM($O$15:V15)))*W3 -> 26227.536 | ... AH15: =MAX(0,MIN($O$15,$F$15-SUM($O$15:AG15)))*AH3 -> 0
D16: =D15+1 -> 2028 | F16: 515124.95 | G16: =F16/$G$11 -> 25756.247 | P16: =G16 -> 25756.247 | Q16: =MAX(0,MIN($P$16,$F$16-SUM($P$16:P16)))*Q3 -> 25756.247 | R16: =MAX(0,MIN($P$16,$F$16-SUM($P$16:Q16)))*R3 -> 25756.247 | S16: =MAX(0,MIN($P$16,$F$16-SUM($P$16:R16)))*S3 -> 25756.247 | T16: =MAX(0,MIN($P$16,$F$16-SUM($P$16:S16)))*T3 -> 25756.247 | U16: =MAX(0,MIN($P$16,$F$16-SUM($P$16:T16)))*U3 -> 25756.247 | V16: =MAX(0,MIN($P$16,$F$16-SUM($P$16:U16)))*V3 -> 25756.247 | W16: =MAX(0,MIN($P$16,$F$16-SUM($P$16:V16)))*W3 -> 25756.247 | X16: =MAX(0,MIN($P$16,$F$16-SUM($P$16:W16)))*X3 -> 0 | ... AH16: =MAX(0,MIN($P$16,$F$16-SUM($P$16:AG16)))*AH3 -> 0
D17: =D16+1 -> 2029 | F17: 504909.39 | G17: =F17/$G$11 -> 25245.47 | Q17: =G17 -> 25245.47 | R17: =MAX(0,MIN($Q$17,$F$17-SUM($Q$17:Q17)))*R3 -> 25245.47 | S17: =MAX(0,MIN($Q$17,$F$17-SUM($Q$17:R17)))*S3 -> 25245.47 | T17: =MAX(0,MIN($Q$17,$F$17-SUM($Q$17:S17)))*T3 -> 25245.47 | U17: =MAX(0,MIN($Q$17,$F$17-SUM($Q$17:T17)))*U3 -> 25245.47 | V17: =MAX(0,MIN($Q$17,$F$17-SUM($Q$17:U17)))*V3 -> 25245.47 | W17: =MAX(0,MIN($Q$17,$F$17-SUM($Q$17:V17)))*W3 -> 25245.47 | X17: =MAX(0,MIN($Q$17,$F$17-SUM($Q$17:W17)))*X3 -> 0 | Y17: =MAX(0,MIN($Q$17,$F$17-SUM($Q$17:X17)))*Y3 -> 0 | ... AH17: =MAX(0,MIN($Q$17,$F$17-SUM($Q$17:AG17)))*AH3 -> 0
D18: =D17+1 -> 2030 | F18: 493883.71 | G18: =F18/$G$11 -> 24694.185 | R18: =G18 -> 24694.185 | S18: =MAX(0,MIN($R$18,$F$18-SUM($R$18:R18)))*S3 -> 24694.185 | T18: =MAX(0,MIN($R$18,$F$18-SUM($R$18:S18)))*T3 -> 24694.185 | U18: =MAX(0,MIN($R$18,$F$18-SUM($R$18:T18)))*U3 -> 24694.185 | V18: =MAX(0,MIN($R$18,$F$18-SUM($R$18:U18)))*V3 -> 24694.185 | W18: =MAX(0,MIN($R$18,$F$18-SUM($R$18:V18)))*W3 -> 24694.185 | X18: =MAX(0,MIN($R$18,$F$18-SUM($R$18:W18)))*X3 -> 0 | Y18: =MAX(0,MIN($R$18,$F$18-SUM($R$18:X18)))*Y3 -> 0 | Z18: =MAX(0,MIN($R$18,$F$18-SUM($R$18:Y18)))*Z3 -> 0 | ... AH18: =MAX(0,MIN($R$18,$F$18-SUM($R$18:AG18)))*AH3 -> 0
D19: =D18+1 -> 2031 | F19: 482027.17 | G19: =F19/$G$11 -> 24101.359 | S19: =G19 -> 24101.359 | T19: =MAX(0,MIN($S$19,$F$19-SUM($S$19:S19)))*T3 -> 24101.359 | U19: =MAX(0,MIN($S$19,$F$19-SUM($S$19:T19)))*U3 -> 24101.359 | V19: =MAX(0,MIN($S$19,$F$19-SUM($S$19:U19)))*V3 -> 24101.359 | W19: =MAX(0,MIN($S$19,$F$19-SUM($S$19:V19)))*W3 -> 24101.359 | X19: =MAX(0,MIN($S$19,$F$19-SUM($S$19:W19)))*X3 -> 0 | Y19: =MAX(0,MIN($S$19,$F$19-SUM($S$19:X19)))*Y3 -> 0 | Z19: =MAX(0,MIN($S$19,$F$19-SUM($S$19:Y19)))*Z3 -> 0 | AA19: =MAX(0,MIN($S$19,$F$19-SUM($S$19:Z19)))*AA3 -> 0 | ... AH19: =MAX(0,MIN($S$19,$F$19-SUM($S$19:AG19)))*AH3 -> 0
D20: =D19+1 -> 2032 | F20: 469318.67 | G20: =F20/$G$11 -> 23465.934 | T20: =G20 -> 23465.934 | U20: =MAX(0,MIN($T$20,$F$20-SUM($T$20:T20)))*U3 -> 23465.934 | V20: =MAX(0,MIN($T$20,$F$20-SUM($T$20:U20)))*V3 -> 23465.934 | W20: =MAX(0,MIN($T$20,$F$20-SUM($T$20:V20)))*W3 -> 23465.934 | X20: =MAX(0,MIN($T$20,$F$20-SUM($T$20:W20)))*X3 -> 0 | Y20: =MAX(0,MIN($T$20,$F$20-SUM($T$20:X20)))*Y3 -> 0 | Z20: =MAX(0,MIN($T$20,$F$20-SUM($T$20:Y20)))*Z3 -> 0 | AA20: =MAX(0,MIN($T$20,$F$20-SUM($T$20:Z20)))*AA3 -> 0 | AB20: =MAX(0,MIN($T$20,$F$20-SUM($T$20:AA20)))*AB3 -> 0 | ... AH20: =MAX(0,MIN($T$20,$F$20-SUM($T$20:AG20)))*AH3 -> 0
D21: =D20+1 -> 2033 | F21: 455736.7 | G21: =F21/$G$11 -> 22786.835 | U21: =G21 -> 22786.835 | V21: =MAX(0,MIN($U$21,$F$21-SUM($U$21:U21)))*V3 -> 22786.835 | W21: =MAX(0,MIN($U$21,$F$21-SUM($U$21:V21)))*W3 -> 22786.835 | X21: =MAX(0,MIN($U$21,$F$21-SUM($U$21:W21)))*X3 -> 0 | Y21: =MAX(0,MIN($U$21,$F$21-SUM($U$21:X21)))*Y3 -> 0 | Z21: =MAX(0,MIN($U$21,$F$21-SUM($U$21:Y21)))*Z3 -> 0 | AA21: =MAX(0,MIN($U$21,$F$21-SUM($U$21:Z21)))*AA3 -> 0 | AB21: =MAX(0,MIN($U$21,$F$21-SUM($U$21:AA21)))*AB3 -> 0 | AC21: =MAX(0,MIN($U$21,$F$21-SUM($U$21:AB21)))*AC3 -> 0 | ... AH21: =MAX(0,MIN($U$21,$F$21-SUM($U$21:AG21)))*AH3 -> 0
D22: =D21+1 -> 2034 | F22: 441259.35 | G22: =F22/$G$11 -> 22062.968 | V22: =G22 -> 22062.968 | W22: =MAX(0,MIN($V$22,$F$22-SUM($V$22:V22)))*W3 -> 22062.968 | X22: =MAX(0,MIN($V$22,$F$22-SUM($V$22:W22)))*X3 -> 0 | Y22: =MAX(0,MIN($V$22,$F$22-SUM($V$22:X22)))*Y3 -> 0 | Z22: =MAX(0,MIN($V$22,$F$22-SUM($V$22:Y22)))*Z3 -> 0 | AA22: =MAX(0,MIN($V$22,$F$22-SUM($V$22:Z22)))*AA3 -> 0 | AB22: =MAX(0,MIN($V$22,$F$22-SUM($V$22:AA22)))*AB3 -> 0 | AC22: =MAX(0,MIN($V$22,$F$22-SUM($V$22:AB22)))*AC3 -> 0 | AD22: =MAX(0,MIN($V$22,$F$22-SUM($V$22:AC22)))*AD3 -> 0 | ... AH22: =MAX(0,MIN($V$22,$F$22-SUM($V$22:AG22)))*AH3 -> 0
D23: =D22+1 -> 2035 | F23: 400813.46 | G23: =F23/$G$11 -> 20040.673 | W23: =G23 -> 20040.673 | X23: =MAX(0,MIN($W$23,$F$23-SUM($W$23:W23)))*X3 -> 0 | Y23: =MAX(0,MIN($W$23,$F$23-SUM($W$23:X23)))*Y3 -> 0 | Z23: =MAX(0,MIN($W$23,$F$23-SUM($W$23:Y23)))*Z3 -> 0 | AA23: =MAX(0,MIN($W$23,$F$23-SUM($W$23:Z23)))*AA3 -> 0 | AB23: =MAX(0,MIN($W$23,$F$23-SUM($W$23:AA23)))*AB3 -> 0 | AC23: =MAX(0,MIN($W$23,$F$23-SUM($W$23:AB23)))*AC3 -> 0 | AD23: =MAX(0,MIN($W$23,$F$23-SUM($W$23:AC23)))*AD3 -> 0 | AE23: =MAX(0,MIN($W$23,$F$23-SUM($W$23:AD23)))*AE3 -> 0 | ... AH23: =MAX(0,MIN($W$23,$F$23-SUM($W$23:AG23)))*AH3 -> 0
D24: Total Depreciation | I24: =SUM(I13:I23)*I3 -> 0 | J24: =SUM(J13:J23)*J3 -> 0 | K24: =SUM(K13:K23)*K3 -> 0 | L24: =SUM(L13:L23)*L3 -> 0 | M24: =SUM(M13:M23)*M3 -> 0 | N24: =SUM(N13:N23)*N3 -> 244444.33 | O24: =SUM(O13:O23)*O3 -> 270671.87 | P24: =SUM(P13:P23)*P3 -> 296428.12 | ... AH24: =SUM(AH13:AH23)*AH3 -> 0

Sheet Data >>

Sheet Service Rev Br-2022
A1: Service revenues
A2: United States | B2: $ | C2: 2,533,165 | D2: $ | E2: 2,017,504 | F2: $ | G2: 1,714,724
A3: International | C3: 319,875 | E3: 274,363 | G3: 232,416
A4: Total service revenues | B4: $ | C4: 2,853,040 | D4: $ | E4: 2,291,867 | F4: $ | G4: 1,947,140

Sheet 2022 - Vehicle Sales
A1: Vehicle sales
A2: United States | B2: $ | C2: 411,985 | D2: $ | E2: 254,568 | F2: $ | G2: 145,962
A3: International | C3: 235,896 | E3: 146,076 | G3: 112,481
A4: Total vehicle sales | B4: $ | C4: 647,881 | D4: $ | E4: 400,644 | F4: $ | G4: 258,443

Sheet 2022 k - BS
A1: ASSETS
A2: Current assets:
A3: Cash, cash equivalents, and restricted cash | B3: $ | C3: 1,384,236 | D3: $ | E3: 1,048,260
A4: Accounts receivable, net | C4: 578,573 | E4: 480,628
A5: Vehicle pooling costs | C5: 112,242 | E5: 94,449
A6: Inventories | C6: 58,791 | E6: 44,968
A7: Income taxes receivable | C7: 49,882 | E7: 20,012
A8: Prepaid expenses and other assets | C8: 18,731 | E8: 14,294
A9: Total current assets | C9: 2,202,455 | E9: 1,702,611
A10: Property and equipment, net | C10: 2,485,764 | E10: 2,296,624
A11: Operating lease right-of-use assets | C11: 116,303 | E11: 119,487
A12: Intangibles, net | C12: 54,680 | E12: 45,873
A13: Goodwill | C13: 401,954 | E13: 355,717
A14: Other assets | C14: 47,708 | E14: 41,831
A15: Total assets | B15: $ | C15: 5,308,864 | D15: $ | E15: 4,562,143
A17: LIABILITIES AND STOCKHOLDERS’ EQUITY
A18: Current liabilities:
A19: Accounts payable and accrued liabilities | B19: $ | C19: 399,034 | D19: $ | E19: 369,826
A20: Deferred revenue | C20: 20,061 | E20: 20,973
A21: Income taxes payable | C21: — | E21: 7,760
A22: Current portion of operating and finance lease liabilities | C22: 21,794 | E22: 22,472
A23: Total current liabilities | C23: 440,889 | E23: 421,031
A24: Deferred income taxes | C24: 80,060 | E24: 63,969
A25: Income taxes payable | C25: 64,637 | E25: 52,345
A26: Operating and finance lease liabilities, net of current portion | C26: 95,683 | E26: 97,961
A27: Long-term debt and other liabilities, net of discount | C27: 1,996 | E27: 397,636
A28: Total liabilities | C28: 683,265 | E28: 1,032,942
A30: Commitments and contingencies
A31: Stockholders’ equity:
A32: Preferred stock: $0.0001 par value—5,000,000 shares authorized; none issued | C32: — | E32: —
A33: Common stock: $0.0001 par value—400,000,000 shares authorized; 238,040,974 and 237,014,273 shares issued and outstanding, respectively | C33: 24 | E33: 24
A34: Additional paid-in capital | C34: 838,532 | E34: 761,834
A35: Accumulated other comprehensive loss | C35: (169,365) | E35: (100,860)
A36: Retained earnings | C36: 3,956,408 | E36: 2,868,203
A37: Total stockholders’ equity | C37: 4,625,599 | E37: 3,529,201
A38: Total liabilities and stockholders’ equity | B38: $ | C38: 5,308,864 | D38: $ | E38: 4,562,143

Sheet 2022 k - IS
A1: Service revenues and vehicle sales:
A2: Service revenues | B2: $ | C2: 2,853,040 | D2: $ | E2: 2,291,867 | F2: $ | G2: 1,947,140
A3: Vehicle sales | C3: 647,881 | E3: 400,644 | G3: 258,443
A4: Total service revenues and vehicle sales | C4: 3,500,921 | E4: 2,692,511 | G4: 2,205,583
A5: Operating expenses:
A6: Yard operations | C6: 1,309,497 | E6: 1,003,292 | G6: 972,487
A7: Cost of vehicle sales | C7: 585,203 | E7: 346,128 | G7: 225,294
A8: General and administrative | C8: 231,224 | E8: 206,665 | G8: 191,703
A9: Total operating expenses | C9: 2,125,924 | E9: 1,556,085 | G9: 1,389,484
A10: Operating income | C10: 1,374,997 | E10: 1,136,426 | G10: 816,099
A11: Other expense:
A12: Interest expense, net | C12: (16,688) | E12: (20,247) | G12: (18,871)
A13: Loss on extinguishment of debt | C13: (16,759) | E13: — | G13: —
A14: Other (expense) income, net | C14: (596) | E14: 5,667 | G14: 3,611
A15: Total other expense | C15: (34,043) | E15: ( 14,580) | G15: (15,260)
A16: Income before income taxes | C16: 1,340,954 | E16: 1,121,846 | G16: 800,839
A17: Income tax expense | C17: 250,824 | E17: 185,351 | G17: 100,932
A18: Net income | B18: $ | C18: 1,090,130 | D18: $ | E18: 936,495 | F18: $ | G18: 699,907
A20: Basic net income per common share | B20: $ | C20: 4.59 | D20: $ | E20: 3.96 | F20: $ | G20: 3.00
A21: Weighted average common shares outstanding | C21: 237,419 | E21: 236,252 | G21: 233,202
A23: Diluted net income per common share | B23: $ | C23: 4.52 | D23: $ | E23: 3.90 | F23: $ | G23: 2.93
A24: Diluted weighted average common shares outstanding | C24: 241,151 | E24: 240,290 | G24: 238,656

Sheet 2022 k - CF
A1: Cash flows from operating activities:
A2: Net income | B2: $ | C2: 1,090,130 | D2: $ | E2: 936,495 | F2: $ | G2: 699,907
A3: Adjustments to reconcile net income to net cash provided by operating activities:
A4: Depreciation and amortization, including debt cost | C4: 138,605 | E4: 123,084 | G4: 104,257
A5: Allowance for credit loss | C5: 1,349 | E5: (1,121) | G5: 1,670
A6: Equity in (earnings) losses of unconsolidated affiliates | C6: 284 | E6: (3,240) | G6: 1,401
A7: Stock-based compensation | C7: 38,965 | E7: 40,922 | G7: 23,322
A8: Gain on sale of property and equipment | C8: (939) | E8: (1,480) | G8: (1,913)
A9: Loss on extinguishment of debt | C9: 16,759 | E9: — | G9: —
A10: Deferred income taxes | C10: 17,017 | E10: (7,951) | G10: 23,082
A11: Changes in operating assets and liabilities, net of effects from acquisitions:
A12: Accounts receivable | C12: (97,750) | E12: (127,513) | G12: 15,993
A13: Vehicle pooling costs | C13: (18,342) | E13: (20,476) | G13: 2,590
A14: Inventories | C14: (10,851) | E14: (24,602) | G14: 1,348
A15: Prepaid expenses and other current and non-current assets | C15: (5,156) | E15: 7,025 | G15: 141
A16: Operating lease right-of-use assets and lease liabilities | C16: 715 | E16: 570 | G16: (572)
A17: Accounts payable and accrued liabilities | C17: 36,306 | E17: 44,613 | G17: 41,648
A18: Deferred revenue | C18: (574) | E18: 8,781 | G18: 1,615
A19: Income taxes receivable | C19: (29,884) | E19: 6,739 | G19: (7,216)
A20: Income taxes payable | C20: 49 | E20: 9,045 | G20: 10,114
A21: Other liabilities | C21: — | E21: — | G21: 498
A22: Net cash provided by operating activities | C22: 1,176,683 | E22: 990,891 | G22: 917,885
A23: Cash flows from investing activities:
A24: Purchases of property and equipment | C24: (337,448) | E24: ( 462,996) | G24: (591,972)
A25: Purchases of assets and liabilities in connection with acquisitions | C25: (106,604) | E25: (5,000) | G25: (11,702)
A26: Proceeds from sale of property and equipment | C26: 4,333 | E26: 2,530 | G26: 2,466
A27: Investment in unconsolidated affiliate | C27: (2,591) | E27: — | G27: —
A28: Purchase of held to maturity securities | C28: (374,866) | E28: — | G28: —
A29: Proceeds from the sale of held to maturity securities | C29: 374,866 | E29: — | G29: —
A30: Net cash used in investing activities | C30: (442,310) | E30: (465,466) | G30: (601,208)
A31: Cash flows from financing activities:
A32: Proceeds from the exercise of stock options | C32: 28,108 | E32: 39,049 | G32: 71,640
A33: Proceeds from the issuance of Employee Stock Purchase Plan shares | C33: 9,625 | E33: 9,136 | G33: 8,276
A34: Payments for employee stock-based tax withholdings | C34: (1,925) | E34: (6,145) | G34: (103,451)
A35: Debt offering costs | C35: (1,212) | E35: — | G35: (2,814)
A36: Principal payments on long-term debt | C36: (416,759) | E36: — | G36: —
A37: Payments of finance lease obligations | C37: (530) | E37: (1,118) | G37: (1,065)
A38: Net cash (used in) provided by financing activities | C38: (382,693) | E38: 40,922 | G38: (27,414)
A39: Effect of foreign currency translation | C39: (15,704) | E39: 4,195 | G39: 2,136
A40: Net increase in cash, cash equivalents, and restricted cash | C40: 335,976 | E40: 570,542 | G40: 291,399
A41: Cash, cash equivalents, and restricted cash at beginning of period | C41: 1,048,260 | E41: 477,718 | G41: 186,319
A42: Cash, cash equivalents, and restricted cash at end of period | B42: $ | C42: 1,384,236 | D42: $ | E42: 1,048,260 | F42: $ | G42: 477,718
A43: Supplemental disclosure of cash flow information:
A44: Interest paid | B44: $ | C44: 18,539 | D44: $ | E44: 19,723 | F44: $ | G44: 19,728
A45: Income taxes paid, net of refunds | B45: $ | C45: 263,226 | D45: $ | E45: 178,241 | F45: $ | G45: 83,770

Sheet 2022 k - PPE
A1: Land | B1: $ | C1: 1,526,446 | D1: $ | E1: 1,428,262
A2: Buildings and improvements | C2: 1,209,331 | E2: 1,126,414
A3: Transportation and other equipment | C3: 429,405 | E3: 326,622
A4: Office furniture and equipment | C4: 84,728 | E4: 79,928
A5: Software | C5: 78,216 | E5: 66,170
C6: 3,328,126 | E6: 3,027,396
A7: Less: Accumulated depreciation and amortization | C7: (842,362) | E7: (730,772)
A8: Property and equipment, net | B8: $ | C8: 2,485,764 | D8: $ | E8: 2,296,624

Sheet 2022 k - Shares
A1: Weighted average common shares outstanding | B1: 237,419 | C1: 236,252 | D1: 233,202
A2: Effect of dilutive securities | B2: 3,732 | C2: 4,038 | D2: 5,454
A3: Weighted average common and dilutive potential common shares outstanding | B3: 241,151 | C3: 240,290 | D3: 238,656

Sheet 2022 k - T61
A1: Service revenues | C1: $ | D1: 2,533,165 | E1: $ | F1: 319,875 | G1: $ | H1: 2,853,040
A2: Vehicle sales | D2: 411,985 | F2: 235,896 | H2: 647,881
A3: Total service revenues and vehicle sales | D3: 2,945,150 | F3: 555,771 | H3: 3,500,921
A4: Yard operations | D4: 1,123,986 | F4: 185,511 | H4: 1,309,497
A5: Cost of vehicle sales | D5: 380,928 | F5: 204,275 | H5: 585,203
A6: General and administrative | D6: 192,667 | F6: 38,557 | H6: 231,224
A7: Operating income | C7: $ | D7: 1,247,569 | E7: $ | F7: 127,428 | G7: $ | H7: 1,374,997
A9: Depreciation and amortization, excluding debt costs | C9: $ | D9: 120,635 | E9: $ | F9: 17,350 | G9: $ | H9: 137,985
A10: Capital expenditures, including acquisitions | D10: 297,632 | F10: 146,420 | H10: 444,052
A11: Total assets | D11: 4,615,788 | F11: 693,076 | H11: 5,308,864
A12: Goodwill | D12: 270,269 | F12: 131,685 | H12: 401,954

Sheet 2022 k - T62
A1: Service revenues | D1: $ | E1: 2,017,504 | F1: $ | G1: 274,363 | H1: $ | I1: 2,291,867
A2: Vehicle sales | E2: 254,568 | G2: 146,076 | I2: 400,644
A3: Total service revenues and vehicle sales | E3: 2,272,072 | G3: 420,439 | I3: 2,692,511
A4: Yard operations | E4: 849,037 | G4: 154,255 | I4: 1,003,292
A5: Cost of vehicle sales | E5: 227,365 | G5: 118,763 | I5: 346,128
A6: General and administrative | E6: 172,115 | G6: 34,550 | I6: 206,665
A7: Operating income | D7: $ | E7: 1,023,555 | F7: $ | G7: 112,871 | H7: $ | I7: 1,136,426
A9: Depreciation and amortization, excluding debt costs | D9: $ | E9: 107,765 | F9: $ | G9: 14,206 | H9: $ | I9: 121,971
A10: Capital expenditures, including acquisitions | E10: 390,706 | G10: 77,290 | I10: 467,996
A11: Total assets | E11: 3,900,712 | G11: 661,431 | I11: 4,562,143
A12: Goodwill | E12: 270,305 | G12: 85,412 | I12: 355,717

Sheet 2022 k - T63
A1: Service revenues | D1: $ | E1: 1,714,724 | F1: $ | G1: 232,416 | H1: $ | I1: 1,947,140
A2: Vehicle sales | E2: 145,962 | G2: 112,481 | I2: 258,443
A3: Total service revenues and vehicle sales | E3: 1,860,686 | G3: 344,897 | I3: 2,205,583
A4: Yard operations | E4: 828,066 | G4: 144,421 | I4: 972,487
A5: Cost of vehicle sales | E5: 135,095 | G5: 90,199 | I5: 225,294
A6: General and administrative | E6: 154,346 | G6: 37,357 | I6: 191,703
A7: Operating income | D7: $ | E7: 743,179 | F7: $ | G7: 72,920 | H7: $ | I7: 816,099
A9: Depreciation and amortization, excluding debt costs | D9: $ | E9: 90,818 | F9: $ | G9: 10,572 | H9: $ | I9: 101,390
A10: Capital expenditures, including acquisitions | E10: 568,773 | G10: 34,901 | I10: 603,674

Sheet 2023 k - Service Rev
A1: Service revenues
A2: United States | B2: $ | C2: 2,841,641 | D2: $ | E2: 2,533,165 | F2: $ | G2: 2,017,504
A3: International | C3: 356,487 | E3: 319,875 | G3: 274,363
A4: Total service revenues | B4: $ | C4: 3,198,128 | D4: $ | E4: 2,853,040 | F4: $ | G4: 2,291,867

Sheet 2023 k - Vehicle Sales
A1: Vehicle sales
A2: United States | B2: $ | C2: 348,007 | D2: $ | E2: 411,985 | F2: $ | G2: 254,568
A3: International | C3: 323,383 | E3: 235,896 | G3: 146,076
A4: Total vehicle sales | B4: $ | C4: 671,390 | D4: $ | E4: 647,881 | F4: $ | G4: 400,644

Sheet 2023 k - BS
A1: ASSETS
A2: Current assets:
A3: Cash, cash equivalents, and restricted cash | B3: $ | C3: 957,395 | D3: $ | E3: 1,384,236
A4: Investment in held to maturity securities | C4: 1,406,589 | E4: —
A5: Accounts receivable, net | C5: 702,038 | E5: 578,573
A6: Vehicle pooling costs | C6: 123,725 | E6: 112,242
A7: Inventories | C7: 39,973 | E7: 58,791
A8: Income taxes receivable | C8: 6,574 | E8: 49,882
A9: Prepaid expenses and other assets | C9: 26,310 | E9: 18,731
A10: Total current assets | C10: 3,262,604 | E10: 2,202,455
A11: Property and equipment, net | C11: 2,844,339 | E11: 2,485,764
A12: Operating lease right-of-use assets | C12: 108,139 | E12: 116,303
A13: Intangibles, net | C13: 62,702 | E13: 54,680
A14: Goodwill | C14: 394,289 | E14: 401,954
A15: Other assets | C15: 65,806 | E15: 47,708
A16: Total assets | B16: $ | C16: 6,737,879 | D16: $ | E16: 5,308,864
A18: LIABILITIES AND STOCKHOLDERS’ EQUITY
A19: Current liabilities:
A20: Accounts payable and accrued liabilities | B20: $ | C20: 440,810 | D20: $ | E20: 399,034
A21: Deferred revenue | C21: 26,117 | E21: 20,061
A22: Income taxes payable | C22: 4,374 | E22: —
A23: Current portion of operating and finance lease liabilities | C23: 21,468 | E23: 21,794
A24: Total current liabilities | C24: 492,769 | E24: 440,889
A25: Deferred income taxes | C25: 89,492 | E25: 80,060
A26: Income taxes payable | C26: 69,193 | E26: 64,637
A27: Operating and finance lease liabilities, net of current portion | C27: 88,082 | E27: 95,683
A28: Long-term debt and other liabilities, net of discount | C28: 10,903 | E28: 1,996
A29: Total liabilities | C29: 750,439 | E29: 683,265
A31: Commitments and contingencies
A32: Stockholders’ equity:
A33: Preferred stock: $0.0001 par value—5,000,000 shares authorized; none issued | C33: — | E33: —
A34: Common stock: $0.0001 par value—1,600,000,000 shares authorized; 957,344,162 and 952,163,896 shares issued and outstanding, respectively | C34: 96 | E34: 96
A35: Additional paid-in capital | C35: 938,910 | E35: 838,460
A36: Accumulated other comprehensive loss | C36: (141,006) | E36: (169,365)
A37: Retained earnings | C37: 5,189,440 | E37: 3,956,408
A38: Total stockholders’ equity | C38: 5,987,440 | E38: 4,625,599
A39: Total liabilities and stockholders’ equity | B39: $ | C39: 6,737,879 | D39: $ | E39: 5,308,864

Sheet 2023 k - IS
A1: Service revenues and vehicle sales:
A2: Service revenues | B2: $ | C2: 3,198,128 | D2: $ | E2: 2,853,040 | F2: $ | G2: 2,291,867
A3: Vehicle sales | C3: 671,390 | E3: 647,881 | G3: 400,644
A4: Total service revenues and vehicle sales | C4: 3,869,518 | E4: 3,500,921 | G4: 2,692,511
A5: Operating expenses:
A6: Yard operations | C6: 1,518,029 | E6: 1,309,497 | G6: 1,003,292
A7: Cost of vehicle sales | C7: 614,498 | E7: 585,203 | G7: 346,128
A8: General and administrative | C8: 250,422 | E8: 231,224 | G8: 206,665
A9: Total operating expenses | C9: 2,382,949 | E9: 2,125,924 | G9: 1,556,085
A10: Operating income | C10: 1,486,569 | E10: 1,374,997 | G10: 1,136,426
A11: Other income (expense):
A12: Interest income (expense), net | C12: 65,928 | E12: ( 16,688) | G12: (20,247)
A13: Loss on extinguishment of debt | C13: — | E13: (16,759) | G13: —
A14: Other income (expense), net | C14: 1,831 | E14: (596) | G14: 5,667
A15: Total other income (expense) | C15: 67,759 | E15: (34,043) | G15: (14,580)
A16: Income before income taxes | C16: 1,554,328 | E16: 1,340,954 | G16: 1,121,846
A17: Income tax expense | C17: 316,587 | E17: 250,824 | G17: 185,351
A18: Net income | B18: $ | C18: 1,237,741 | D18: $ | E18: 1,090,130 | F18: $ | G18: 936,495
A20: Basic net income per common share | B20: $ | C20: 1.30 | D20: $ | E20: 1.15 | F20: $ | G20: 0.99
A21: Weighted average common shares outstanding | C21: 953,574 | E21: 949,676 | G21: 945,008
A23: Diluted net income per common share | B23: $ | C23: 1.28 | D23: $ | E23: 1.13 | F23: $ | G23: 0.97
A24: Diluted weighted average common shares outstanding | C24: 966,647 | E24: 964,604 | G24: 961,160

Sheet 2023 k - CF
A1: Cash flows from operating activities:
A2: Net income | B2: $ | C2: 1,237,741 | D2: $ | E2: 1,090,130 | F2: $ | G2: 936,495
A3: Adjustments to reconcile net income to net cash provided by operating activities:
A4: Depreciation and amortization, including debt cost | C4: 159,684 | E4: 138,605 | G4: 123,084
A5: Allowance for credit losses (gains) | C5: 1,946 | E5: 1,349 | G5: (1,121)
A6: Equity in losses (earnings) of unconsolidated affiliates | C6: 5,347 | E6: 284 | G6: (3,240)
A7: Stock-based compensation | C7: 39,673 | E7: 38,965 | G7: 40,922
A8: Gain on sale of property and equipment | C8: (1,846) | E8: (939) | G8: (1,480)
A9: Loss on extinguishment of debt | C9: — | E9: 16,759 | G9: —
A10: Deferred income taxes (benefits) | C10: 9,946 | E10: 17,017 | G10: (7,951)
A11: Changes in operating assets and liabilities, net of effects from acquisitions:
A12: Accounts receivable | C12: (123,207) | E12: (97,750) | G12: (127,513)
A13: Vehicle pooling costs | C13: (10,989) | E13: (18,342) | G13: (20,476)
A14: Inventories | C14: 26,549 | E14: (10,851) | G14: (24,602)
A15: Prepaid expenses and other current and non-current assets | C15: (59,949) | E15: (5,156) | G15: 7,025
A16: Operating lease right-of-use assets and lease liabilities | C16: 350 | E16: 715 | G16: 570
A17: Accounts payable and accrued liabilities | C17: 18,010 | E17: 36,306 | G17: 44,613
A18: Deferred revenue | C18: 5,896 | E18: (574) | G18: 8,781
A19: Income taxes receivable | C19: 33,193 | E19: (29,884) | G19: 6,739
A20: Income taxes payable | C20: 21,866 | E20: 49 | G20: 9,045
A21: Net cash provided by operating activities | C21: 1,364,210 | E21: 1,176,683 | G21: 990,891
A22: Cash flows from investing activities:
A23: Purchases of property and equipment | C23: (516,636) | E23: (337,448) | G23: (462,996)
A24: Proceeds from sale of property and equipment | C24: 33,919 | E24: 4,333 | G24: 2,530
A25: Purchases of assets and liabilities in connection with acquisitions | C25: — | E25: (106,604) | G25: (5,000)
A26: Investment in held to maturity securities | C26: (1,406,588) | E26: (374,866) | G26: —
A27: Proceeds from the sale of held to maturity securities | C27: — | E27: 374,866 | G27: —
A28: Investment in unconsolidated affiliate | C28: (2,744) | E28: (2,591) | G28: —
A29: Net cash used in investing activities | C29: (1,892,049) | E29: (442,310) | G29: (465,466)
A30: Cash flows from financing activities:
A31: Proceeds from the exercise of stock options | C31: 49,679 | E31: 28,108 | G31: 39,049
A32: Proceeds from the issuance of Employee Stock Purchase Plan shares | C32: 11,098 | E32: 9,625 | G32: 9,136
A33: Payments for employee stock-based tax withholdings | C33: (4,709) | E33: (1,925) | G33: (6,145)
A34: Issuance of principal on revolver facility | C34: 44,494 | E34: — | G34: —
A35: Principal payments on revolver facility | C35: (33,924) | E35: — | G35: —
A36: Debt offering costs | C36: — | E36: (1,212) | G36: —
A37: Principal payments on long-term debt | C37: — | E37: (416,759) | G37: —
A38: Payments of finance lease obligations | C38: (23) | E38: (530) | G38: (1,118)
A39: Net cash provided by (used in) financing activities | C39: 66,615 | E39: (382,693) | G39: 40,922
A40: Effect of foreign currency translation | C40: 34,383 | E40: (15,704 ) | G40: 4,195
A41: Net (decrease) increase in cash, cash equivalents, and restricted cash | C41: (426,841) | E41: 335,976 | G41: 570,542
A42: Cash, cash equivalents, and restricted cash at beginning of period | C42: 1,384,236 | E42: 1,048,260 | G42: 477,718
A43: Cash, cash equivalents, and restricted cash at end of period | B43: $ | C43: 957,395 | D43: $ | E43: 1,384,236 | F43: $ | G43: 1,048,260
A44: Supplemental disclosure of cash flow information:
A45: Interest paid | B45: $ | C45: 2,614 | D45: $ | E45: 18,539 | F45: $ | G45: 19,723
A46: Income taxes paid, net of refunds | B46: $ | C46: 257,514 | D46: $ | E46: 263,226 | F46: $ | G46: 178,241

Sheet 2023 k - PPE
A1: Land | B1: $ | C1: 1,812,001 | D1: $ | F1: 1,526,446
A2: Buildings and improvements | C2: 1,339,820 | F2: 1,209,331
A3: Transportation and other equipment | C3: 490,136 | F3: 429,405
A4: Office furniture and equipment | C4: 91,031 | F4: 84,728
A5: Software | C5: 89,575 | F5: 78,216
C6: 3,822,563 | F6: 3,328,126
A7: Less: Accumulated depreciation and amortization | C7: (978,224) | F7: (842,362)
A8: Property and equipment, net | B8: $ | C8: 2,844,339 | D8: $ | F8: 2,485,764

Sheet 2023 k - Shares
A1: Weighted average common shares outstanding | B1: 953,574 | C1: 949,676 | D1: 945,008
A2: Effect of dilutive securities | B2: 13,073 | C2: 14,928 | D2: 16,152
A3: Weighted average common and dilutive potential common shares outstanding | B3: 966,647 | C3: 964,604 | D3: 961,160

Sheet 2023 k - T59
A1: Service revenues | C1: $ | D1: 2,841,641 | E1: $ | F1: 356,487 | G1: $ | H1: 3,198,128
A2: Vehicle sales | D2: 348,007 | F2: 323,383 | H2: 671,390
A3: Total service revenues and vehicle sales | D3: 3,189,648 | F3: 679,870 | H3: 3,869,518
A4: Yard operations | D4: 1,292,527 | F4: 225,502 | H4: 1,518,029
A5: Cost of vehicle sales | D5: 326,764 | F5: 287,734 | H5: 614,498
A6: General and administrative | D6: 202,260 | F6: 48,162 | H6: 250,422
A7: Operating income | C7: $ | D7: 1,368,097 | E7: $ | F7: 118,472 | G7: $ | H7: 1,486,569
A9: Depreciation and amortization, excluding debt costs | C9: $ | D9: 135,804 | E9: $ | F9: 23,674 | G9: $ | H9: 159,478
A10: Capital expenditures, including acquisitions | D10: 373,190 | F10: 143,446 | H10: 516,636
A11: Total assets | D11: 5,825,064 | F11: 912,815 | H11: 6,737,879
A12: Goodwill | D12: 270,269 | F12: 124,020 | H12: 394,289

Sheet 2023 k - T60
A1: Service revenues | D1: $ | E1: 2,533,165 | F1: $ | G1: 319,875 | H1: $ | I1: 2,853,040
A2: Vehicle sales | E2: 411,985 | G2: 235,896 | I2: 647,881
A3: Total service revenues and vehicle sales | E3: 2,945,150 | G3: 555,771 | I3: 3,500,921
A4: Yard operations | E4: 1,123,986 | G4: 185,511 | I4: 1,309,497
A5: Cost of vehicle sales | E5: 380,928 | G5: 204,275 | I5: 585,203
A6: General and administrative | E6: 192,667 | G6: 38,557 | I6: 231,224
A7: Operating income | D7: $ | E7: 1,247,569 | F7: $ | G7: 127,428 | H7: $ | I7: 1,374,997
A9: Depreciation and amortization, excluding debt costs | D9: $ | E9: 120,635 | F9: $ | G9: 17,350 | H9: $ | I9: 137,985
A10: Capital expenditures, including acquisitions | E10: 297,632 | G10: 146,420 | I10: 444,052
A11: Total assets | E11: 4,615,788 | G11: 693,076 | I11: 5,308,864
A12: Goodwill | E12: 270,269 | G12: 131,685 | I12: 401,954

Sheet 2023 k - T61
A1: Service revenues | D1: $ | E1: 2,017,504 | F1: $ | G1: 274,363 | H1: $ | I1: 2,291,867
A2: Vehicle sales | E2: 254,568 | G2: 146,076 | I2: 400,644
A3: Total service revenues and vehicle sales | E3: 2,272,072 | G3: 420,439 | I3: 2,692,511
A4: Yard operations | E4: 849,037 | G4: 154,255 | I4: 1,003,292
A5: Cost of vehicle sales | E5: 227,365 | G5: 118,763 | I5: 346,128
A6: General and administrative | E6: 172,115 | G6: 34,550 | I6: 206,665
A7: Operating income | D7: $ | E7: 1,023,555 | F7: $ | G7: 112,871 | H7: $ | I7: 1,136,426
A9: Depreciation and amortization, excluding debt costs | D9: $ | E9: 107,765 | F9: $ | G9: 14,206 | H9: $ | I9: 121,971
A10: Capital expenditures, including acquisitions | E10: 390,706 | G10: 77,290 | I10: 467,996

Sheet 2024 k - Service Rev
A1: Service revenues
A2: United States | B2: $ | C2: 3,126,102 | D2: $ | E2: 2,841,641 | F2: $ | G2: 2,533,165
A3: International | C3: 434,900 | E3: 356,487 | G3: 319,875
A4: Total service revenues | B4: $ | C4: 3,561,002 | D4: $ | E4: 3,198,128 | F4: $ | G4: 2,853,040

Sheet 2024 k - Vehicle Sales
A1: Vehicle sales
A2: United States | B2: $ | C2: 338,633 | D2: $ | E2: 348,007 | F2: $ | G2: 411,985
A3: International | C3: 337,188 | E3: 323,383 | G3: 235,896
A4: Total vehicle sales | B4: $ | C4: 675,821 | D4: $ | E4: 671,390 | F4: $ | G4: 647,881

Sheet 2024 k - BS
A1: ASSETS
A2: Current assets:
A3: Cash, cash equivalents, and restricted cash $ | B3: 1,514,111 | C3: $ | D3: 957,395
A4: Investment in held to maturity securities | B4: 1,908,047 | D4: 1,406,589
A5: Accounts receivable, net | B5: 785,877 | D5: 702,038
A6: Vehicle pooling costs | B6: 132,638 | D6: 123,725
A7: Inventories | B7: 43,639 | D7: 39,973
A8: Income taxes receivable | B8: — | D8: 6,574
A9: Prepaid expenses and other assets | B9: 33,872 | D9: 26,310
A10: Total current assets | B10: 4,418,184 | D10: 3,262,604
A11: Property and equipment, net | B11: 3,175,838 | D11: 2,844,339
A12: Operating lease right-of-use assets | B12: 116,301 | D12: 108,139
A13: Intangibles, net | B13: 0h0 | C13: 74,088 | E13: 62,702
A14: Goodwill | C14: 513,909 | E14: 394,289
A15: Other assets | C15: 129,444 | E15: 65,806
A16: Total assets | B16: $ | C16: 8,427,764 | D16: $ | E16: 6,737,879
B17: LIABILITIES, REDEEMABLE NONCONTROLLING INTERESTS AND STOCKHOLDERS’ EQUITY
A18: Current liabilities:
A19: Accounts payable and accrued liabilities | B19: $ | C19: 518,148 | D19: $ | E19: 440,810
A20: Deferred revenue | C20: 28,121 | E20: 26,117
A21: Income taxes payable | C21: 60,994 | E21: 4,374
A22: Current portion of operating and finance lease liabilities | C22: 21,304 | E22: 21,468
A23: Total current liabilities | C23: 628,567 | E23: 492,769
A24: Deferred income taxes | C24: 93,653 | E24: 89,492
A25: Income taxes payable | C25: 59,560 | E25: 69,193
A26: Operating and finance lease liabilities, net of current portion | C26: 97,429 | E26: 88,082
A27: Long-term debt and other liabilities, net of discount | C27: — | E27: 10,903
A28: Total liabilities | C28: 879,209 | E28: 750,439
A29: Commitments and contingencies
A30: Redeemable non-controlling interest | C30: 24,544 | E30: —
A31: Stockholders’ equity:
A32: Preferred stock: $0.0001 par value—5,000,000 shares authorized; none issued | C32: — | E32: —
A33: Common stock: $0.0001 par value—1,600,000,000 shares authorized; 962,967,011 and 957,344,162 shares issued and outstanding, respectively | C33: 96 | E33: 96
A34: Additional paid-in capital | C34: 1,120,985 | E34: 938,910
A35: Accumulated other comprehensive loss | C35: (142,972) | E35: (141,006)
A36: Retained earnings | C36: 6,545,902 | E36: 5,189,440
A37: Total stockholders’ equity | C37: 7,524,011 | E37: 5,987,440
A38: Total liabilities, redeemable noncontrolling interests and stockholders’ equity | B38: $ | C38: 8,427,764 | D38: $ | E38: 6,737,879

Sheet 2024 k - IS
A1: Service revenues and vehicle sales:
A2: Service revenues | B2: $ | C2: 3,561,002 | D2: $ | E2: 3,198,128 | F2: $ | G2: 2,853,040
A3: Vehicle sales | C3: 675,821 | E3: 671,390 | G3: 647,881
A4: Total service revenues and vehicle sales | C4: 4,236,823 | E4: 3,869,518 | G4: 3,500,921
A5: Operating expenses:
A6: Yard operations | C6: 1,710,084 | E6: 1,518,029 | G6: 1,309,497
A7: Cost of vehicle sales | C7: 619,487 | E7: 614,498 | G7: 585,203
A8: General and administrative | C8: 335,229 | E8: 250,422 | G8: 231,224
A9: Total operating expenses | C9: 2,664,800 | E9: 2,382,949 | G9: 2,125,924
A10: Operating income | C10: 1,572,023 | E10: 1,486,569 | G10: 1,374,997
A11: Other income (expense):
A12: Interest income (expense), net | C12: 145,673 | E12: 65,928 | G12: (16,688)
A13: Loss on extinguishment of debt | C13: — | E13: — | G13: (16,759)
A14: Other income (expense), net | C14: (3,095) | E14: 1,831 | G14: (596)
A15: Total other income | C15: 142,578 | E15: 67,759 | G15: ( 34,043)
A16: Income before income taxes | C16: 1,714,601 | E16: 1,554,328 | G16: 1,340,954
A17: Income tax expense | C17: 352,254 | E17: 316,587 | G17: 250,824
A18: Net income | C18: 1,362,347 | E18: 1,237,741 | G18: 1,090,130
A19: Less: Net income (loss) attributable to redeemable noncontrolling interest | C19: (673) | E19: — | G19: —
A20: Net income attributable to Copart, Inc. | B20: $ | C20: 1,363,020 | D20: $ | E20: 1,237,741 | F20: $ | G20: 1,090,130
A22: Basic net income per common share | B22: $ | C22: 1.42 | D22: $ | E22: 1.30 | F22: $ | G22: 1.15
A23: Weighted average common shares outstanding | C23: 960,739 | E23: 953,574 | G23: 949,676
A25: Diluted net income per common share | B25: $ | C25: 1.40 | D25: $ | E25: 1.28 | F25: $ | G25: 1.13
A26: Diluted weighted average common shares outstanding | C26: 974,798 | E26: 966,647 | G26: 964,604

Sheet 2024 k - cf
A1: Cash flows from operating activities:
A2: Net income | C2: $ | D2: 1,362,347 | E2: $ | F2: 1,237,741 | G2: $ | H2: 1,090,130
A3: Adjustments to reconcile net income to net cash provided by operating activities:
A4: Depreciation and amortization, including debt cost | D4: 190,256 | F4: 159,684 | H4: 138,605
A5: Allowance for credit losses | D5: 3,914 | F5: 1,946 | H5: 1,349
A6: Gain on extinguishment of liabilities | D6: (4,058) | F6: — | H6: —
A7: Equity in losses of unconsolidated affiliates | D7: 2,241 | F7: 5,347 | H7: 284
A8: Stock-based compensation | D8: 35,234 | F8: 39,673 | H8: 38,965
A9: Gain on sale of property and equipment | D9: (2,386) | F9: (1,846) | H9: (939)
A10: Loss on extinguishment of debt | D10: — | F10: — | H10: 16,759
A11: Deferred income (benefits) taxes | D11: (847) | F11: 9,946 | H11: 17,017
A12: Changes in operating assets and liabilities, net of effects from acquisitions:
A13: Accounts receivable | D13: (145,385) | F13: (123,207) | H13: (97,750)
A14: Vehicle pooling costs | D14: (9,542) | F14: (10,989) | H14: (18,342)
A15: Inventories | D15: (3,698) | F15: 26,549 | H15: (10,851)
A16: Prepaid expenses and other current and non-current assets | D16: (71,067) | F16: (59,949) | H16: (5,156)
A17: Operating lease right-of-use assets and lease liabilities | D17: 1,064 | F17: 350 | H17: 715
A18: Accounts payable and accrued liabilities | D18: 59,528 | F18: 18,010 | H18: 36,306
A19: Deferred revenue | D19: 1,867 | F19: 5,896 | H19: (574)
A20: Income taxes receivable | D20: 6,561 | F20: 33,193 | H20: (29,884)
A21: Income taxes payable | D21: 46,535 | F21: 21,866 | H21: 49
A22: Net cash provided by operating activities | D22: 1,472,564 | F22: 1,364,210 | H22: 1,176,683
A23: Cash flows from investing activities:
A24: Purchases of property and equipment | D24: (510,990) | F24: (516,636) | H24: (337,448)
A25: Assets and liabilities acquired in connection with acquisition | D25: 17,662 | F25: — | H25: (106,604)
A26: Proceeds from sale of property and equipment | D26: 4,166 | F26: 33,919 | H26: 4,333
A27: Investment in held to maturity securities | D27: (4,087,162) | F27: (1,406,588) | H27: (374,866)
A28: Proceeds from the sale of held to maturity securities | D28: 3,645,000 | F28: — | H28: 374,866
A29: Investment in unconsolidated affiliate | D29: (8,755) | F29: (2,744) | H29: (2,591)
A30: Net cash used in investing activities | D30: (940,079) | F30: (1,892,049) | H30: (442,310)
A31: Cash flows from financing activities:
A32: Proceeds from the exercise of stock options | D32: 24,260 | F32: 49,679 | H32: 28,108
A33: Proceeds from the issuance of Employee Stock Purchase Plan shares | D33: 12,406 | F33: 11,098 | H33: 9,625
A34: Payments for employee stock-based tax withholdings | D34: (6,558) | F34: (4,709) | H34: (1,925)
A35: Issuance of principal on revolver facility | D35: — | F35: 44,494 | H35: —
A36: Principal payments on revolver facility | D36: (10,821) | F36: (33,924) | H36: —
A37: Debt offering costs | D37: — | F37: — | H37: (1,212)
A38: Principal payments on long-term debt | D38: — | F38: — | H38: (416,759)
A39: Payments of finance lease obligations | D39: (14) | F39: (23) | H39: (530)
A40: Net cash provided by (used in) financing activities | D40: 19,273 | F40: 66,615 | H40: (382,693)
A41: Effect of foreign currency translation | D41: 4,958 | F41: 34,383 | H41: (15,704)
A42: Net (decrease) increase in cash, cash equivalents, and restricted cash | D42: 556,716 | F42: (426,841) | H42: 335,976
A43: Cash, cash equivalents, and restricted cash at beginning of period | D43: 957,395 | F43: 1,384,236 | H43: 1,048,260
A44: Cash, cash equivalents, and restricted cash at end of period | C44: $ | D44: 1,514,111 | E44: $ | F44: 957,395 | G44: $ | H44: 1,384,236
A45: Supplemental disclosure of cash flow information:
A46: Interest paid | C46: $ | D46: 3,127 | E46: $ | F46: 2,614 | G46: $ | H46: 18,539
A47: Income taxes paid, net of refunds | C47: $ | D47: 285,891 | E47: $ | F47: 257,514 | G47: $ | H47: 263,226

Sheet 2024 k - PPE
A1: Land | C1: $ | D1: 2,027,639 | E1: $ | F1: 1,812,001
A2: Buildings and improvements | D2: 1,482,891 | F2: 1,339,820
A3: Transportation and other equipment | D3: 604,977 | F3: 490,136
A4: Office furniture and equipment | D4: 97,576 | F4: 91,031
A5: Software | D5: 105,001 | F5: 89,575
D6: 4,318,084 | F6: 3,822,563
A7: Less: Accumulated depreciation and amortization | D7: (1,142,246) | F7: (978,224)
A8: Property and equipment, net | C8: $ | D8: 3,175,838 | E8: $ | F8: 2,844,339

Sheet 2024 k - Shares
A1: Weighted average common shares outstanding | B1: 960,739 | C1: 953,574 | D1: 949,676
A2: Effect of dilutive securities | B2: 14,059 | C2: 13,073 | D2: 14,928
A3: Weighted average common and dilutive potential common shares outstanding | B3: 974,798 | C3: 966,647 | D3: 964,604

Sheet 2024 k - T60
A1: Service revenues | C1: $ | D1: 3,126,102 | E1: $ | F1: 434,900 | G1: $ | H1: 3,561,002
A2: Vehicle sales | D2: 338,633 | F2: 337,188 | H2: 675,821
A3: Total service revenues and vehicle sales | D3: 3,464,735 | F3: 772,088 | H3: 4,236,823
A4: Yard operations | D4: 1,440,707 | F4: 269,377 | H4: 1,710,084
A5: Cost of vehicle sales | D5: 313,449 | F5: 306,038 | H5: 619,487
A6: General and administrative | D6: 282,545 | F6: 52,684 | H6: 335,229
A7: Operating income | C7: $ | D7: 1,428,034 | E7: $ | F7: 143,989 | G7: $ | H7: 1,572,023
A9: Depreciation and amortization, excluding debt costs | C9: $ | D9: 161,685 | E9: $ | F9: 28,076 | G9: $ | H9: 189,761
A10: Capital expenditures, including acquisitions | D10: 491,497 | F10: 113,906 | H10: 605,403
A11: Total assets | D11: 7,386,103 | F11: 1,041,661 | H11: 8,427,764
A12: Goodwill | D12: 390,421 | F12: 123,488 | H12: 513,909

Sheet 2024 k - T61
A1: Service revenues | D1: $ | E1: 2,841,641 | F1: $ | G1: 356,487 | H1: $ | I1: 3,198,128
A2: Vehicle sales | E2: 348,007 | G2: 323,383 | I2: 671,390
A3: Total service revenues and vehicle sales | E3: 3,189,648 | G3: 679,870 | I3: 3,869,518
A4: Yard operations | E4: 1,292,527 | G4: 225,502 | I4: 1,518,029
A5: Cost of vehicle sales | E5: 326,764 | G5: 287,734 | I5: 614,498
A6: General and administrative | E6: 202,260 | G6: 48,162 | I6: 250,422
A7: Operating income | D7: $ | E7: 1,368,097 | F7: $ | G7: 118,472 | H7: $ | I7: 1,486,569
A9: Depreciation and amortization, excluding debt costs | D9: $ | E9: 135,804 | F9: $ | G9: 23,674 | H9: $ | I9: 159,478
A10: Capital expenditures, including acquisitions | E10: 373,190 | G10: 143,446 | I10: 516,636
A11: Total assets | E11: 5,825,064 | G11: 912,815 | I11: 6,737,879
A12: Goodwill | E12: 270,269 | G12: 124,020 | I12: 394,289

Sheet 2024 k - T62
A1: Service revenues | B1: $ | C1: 2,533,165 | D1: $ | E1: 319,875 | F1: $ | G1: 2,853,040
A2: Vehicle sales | C2: 411,985 | E2: 235,896 | G2: 647,881
A3: Total service revenues and vehicle sales | C3: 2,945,150 | E3: 555,771 | G3: 3,500,921
A4: Yard operations | C4: 1,123,986 | E4: 185,511 | G4: 1,309,497
A5: Cost of vehicle sales | C5: 380,928 | E5: 204,275 | G5: 585,203
A6: General and administrative | C6: 192,667 | E6: 38,557 | G6: 231,224
A7: Operating income | B7: $ | C7: 1,247,569 | D7: $ | E7: 127,428 | F7: $ | G7: 1,374,997
A9: Depreciation and amortization, excluding debt costs | B9: $ | C9: 120,635 | D9: $ | E9: 17,350 | F9: $ | G9: 137,985
A10: Capital expenditures, including acquisitions | C10: 297,632 | E10: 146,420 | G10: 444,052
A11: Total assets | C11: 4,615,788 | E11: 693,076 | G11: 5,308,864
A12: Goodwill | C12: 270,269 | E12: 131,685 | G12: 401,954

Sheet 2025 k - BS
A1: ASSETS
A2: Current assets:
A3: Cash, cash equivalents, and restricted cash $ | C3: 2,780,531 | E3: 1,514,111
A4: Investment in held to maturity securities | C4: 2,008,539 | E4: 1,908,047
A5: Accounts receivable, net | C5: 762,811 | E5: 785,877
A6: Vehicle pooling costs | C6: 116,145 | E6: 132,638
A7: Inventories | C7: 39,661 | E7: 43,639
A8: Income taxes receivable | C8: 580 | E8: —
A9: Prepaid expenses and other assets | C9: 46,361 | E9: 33,872
A10: Total current assets | C10: 5,754,628 | E10: 4,418,184
A11: Property and equipment, net | C11: 3,598,093 | E11: 3,175,838
A12: Operating lease right-of-use assets | C12: 99,708 | E12: 116,301
A13: Intangibles, net | C13: 62,832 | E13: 74,088
A14: Goodwill | C14: 517,779 | E14: 513,909
A15: Other assets | C15: 57,862 | E15: 129,444
A16: Total assets | B16: $ | C16: 10,090,902 | D16: $ | E16: 8,427,764
B17: LIABILITIES, REDEEMABLE NONCONTROLLING INTERESTS AND STOCKHOLDERS’ EQUITY
A18: Current liabilities:
A19: Accounts payable and accrued liabilities | B19: $ | C19: 591,831 | D19: $ | E19: 518,148
A20: Deferred revenue | C20: 30,440 | E20: 28,121
A21: Income taxes payable | C21: 41,141 | E21: 60,994
A22: Current portion of operating and finance lease liabilities | C22: 19,869 | E22: 21,304
A23: Total current liabilities | C23: 683,281 | E23: 628,567
A24: Deferred income taxes | C24: 80,625 | E24: 93,653
A25: Income taxes payable | C25: 35,635 | E25: 59,560
A26: Operating and finance lease liabilities, net of current portion | C26: 83,870 | E26: 97,429
A27: Total liabilities | C27: 883,411 | E27: 879,209
A28: Commitments and contingencies
A29: Redeemable non-controlling interest | C29: 20,458 | E29: 24,544
A30: Stockholders’ equity:
A31: Preferred stock: $0.0001 par value—5,000,000 shares authorized; none issued | C31: — | E31: —
A32: Common stock: $0.0001 par value—1,600,000,000 shares authorized; 967,478,690 and 962,967,011 shares issued and outstanding, respectively | C32: 97 | E32: 96
A33: Additional paid-in capital | C33: 1,214,150 | E33: 1,120,985
A34: Accumulated other comprehensive loss | C34: (120,283) | E34: (142,972)
A35: Retained earnings | C35: 8,093,069 | E35: 6,545,902
A36: Total stockholders’ equity | C36: 9,187,033 | E36: 7,524,011
A37: Total liabilities, redeemable noncontrolling interests and stockholders’ equity | B37: $ | C37: 10,090,902 | D37: $ | E37: 8,427,764

Sheet 2025 k - IS
A1: Service revenues and vehicle sales:
A2: Service revenues | B2: $ | C2: 3,968,662 | D2: $ | E2: 3,561,002 | F2: $ | G2: 3,198,128
A3: Vehicle sales | C3: 678,296 | E3: 675,821 | G3: 671,390
A4: Total service revenues and vehicle sales | C4: 4,646,958 | E4: 4,236,823 | G4: 3,869,518
A5: Operating expenses:
A6: Facility operations | C6: 1,944,318 | E6: 1,710,084 | G6: 1,518,029
A7: Cost of vehicle sales | C7: 602,997 | E7: 619,487 | G7: 614,498
A8: General and administrative | C8: 402,929 | E8: 335,229 | G8: 250,422
A9: Total operating expenses | C9: 2,950,244 | E9: 2,664,800 | G9: 2,382,949
A10: Operating income | C10: 1,696,714 | E10: 1,572,023 | G10: 1,486,569
A11: Other income (expense):
A12: Interest income (expense), net | C12: 178,909 | E12: 145,673 | G12: 65,928
A13: Other income (expense), net | C13: 19,958 | E13: (3,095) | G13: 1,831
A14: Total other income | C14: 198,867 | E14: 142,578 | G14: 67,759
A15: Income before income taxes | C15: 1,895,581 | E15: 1,714,601 | G15: 1,554,328
A16: Income tax expense | C16: 347,218 | E16: 352,254 | G16: 316,587
A17: Net income | C17: 1,548,363 | E17: 1,362,347 | G17: 1,237,741
A18: Less: Net income (loss) attributable to redeemable noncontrolling interest | C18: (4,086) | E18: (673) | G18: —
A19: Net income attributable to Copart, Inc. | B19: $ | C19: 1,552,449 | D19: $ | E19: 1,363,020 | F19: $ | G19: 1,237,741
A21: Basic net income per common share | B21: $ | C21: 1.61 | D21: $ | E21: 1.42 | F21: $ | G21: 1.30
A22: Weighted average common shares outstanding | C22: 965,306 | E22: 960,739 | G22: 953,574
A24: Diluted net income per common share | B24: $ | C24: 1.59 | D24: $ | E24: 1.40 | F24: $ | G24: 1.28
A25: Diluted weighted average common shares outstanding | C25: 977,563 | E25: 974,798 | G25: 966,647

Sheet 2025 k - CF
A1: Cash flows from operating activities:
A2: Net income | B2: $ | C2: 1,548,363 | D2: $ | E2: 1,362,347 | F2: $ | G2: 1,237,741
A3: Adjustments to reconcile net income to net cash provided by operating activities:
A4: Depreciation and amortization, including debt cost | C4: 217,784 | E4: 190,256 | G4: 159,684
A5: Allowance for credit losses | C5: 354 | E5: 3,914 | G5: 1,946
A6: Gain on extinguishment of liabilities | C6: — | E6: (4,058) | G6: —
A7: Equity in (income) losses of unconsolidated affiliates | C7: (149) | E7: 2,241 | G7: 5,347
A8: Stock-based compensation | C8: 38,004 | E8: 35,234 | G8: 39,673
A9: Gain on sale of property and equipment | C9: (13,726) | E9: (2,386) | G9: (1,846)
A10: Deferred income (benefits) taxes | C10: (13,440) | E10: (847) | G10: 9,946
A11: Changes in operating assets and liabilities, net of effects from acquisitions:
A12: Accounts receivable | C12: (33,950) | E12: ( 145,385) | G12: (123,207)
A13: Vehicle pooling costs | C13: 16,705 | E13: (9,542) | G13: (10,989)
A14: Inventories | C14: 4,655 | E14: (3,698) | G14: 26,549
A15: Prepaid expenses and other current and non-current assets | C15: 7,748 | E15: (71,067) | G15: (59,949)
A16: Operating lease right-of-use assets and lease liabilities | C16: 478 | E16: 1,064 | G16: 350
A17: Accounts payable and accrued liabilities | C17: 69,599 | E17: 59,528 | G17: 18,010
A18: Deferred revenue | C18: 2,159 | E18: 1,867 | G18: 5,896
A19: Income taxes receivable | C19: (575) | E19: 6,561 | G19: 33,193
A20: Income taxes payable | C20: (44,259) | E20: 46,535 | G20: 21,866
A21: Net cash provided by operating activities | C21: 1,799,750 | E21: 1,472,564 | G21: 1,364,210
A22: Cash flows from investing activities:
A23: Purchases of property and equipment | C23: (568,990) | E23: (510,990) | G23: (516,636)
A24: Assets and liabilities acquired in connection with acquisition | C24: (1,223) | E24: 17,662 | G24: —
A25: Proceeds from sale of property and equipment | C25: 31,831 | E25: 4,166 | G25: 33,919
A26: Investment in held to maturity securities | C26: (4,001,918) | E26: (4,087,162) | G26: (1,406,588)
A27: Proceeds from held to maturity securities | C27: 3,960,000 | E27: 3,645,000 | G27: —
A28: Investment in unconsolidated affiliate | C28: (7,148) | E28: (8,755) | G28: (2,744)
A29: Net cash used in investing activities | C29: (587,448) | E29: (940,079) | G29: (1,892,049)
A30: Cash flows from financing activities:
A31: Proceeds from the exercise of stock options | C31: 42,759 | E31: 24,260 | G31: 49,679
A32: Proceeds from the issuance of Employee Stock Purchase Plan shares | C32: 14,679 | E32: 12,406 | G32: 11,098
A33: Payments for employee stock-based tax withholdings | C33: (5,282) | E33: (6,558) | G33: (4,709)
A34: Issuance of principal on revolver facility | C34: — | E34: — | G34: 44,494
A35: Principal payments on revolver facility | C35: — | E35: (10,821) | G35: (33,924)
A36: Payments of finance lease obligations | C36: (49) | E36: (14) | G36: (23)
A37: Net cash provided by financing activities | C37: 52,107 | E37: 19,273 | G37: 66,615
A38: Effect of foreign currency translation | C38: 2,011 | E38: 4,958 | G38: 34,383
A39: Net increase (decrease) in cash, cash equivalents, and restricted cash | C39: 1,266,420 | E39: 556,716 | G39: (426,841)
A40: Cash, cash equivalents, and restricted cash at beginning of period | C40: 1,514,111 | E40: 957,395 | G40: 1,384,236
A41: Cash, cash equivalents, and restricted cash at end of period | B41: $ | C41: 2,780,531 | D41: $ | E41: 1,514,111 | F41: $ | G41: 957,395
A42: Supplemental disclosure of cash flow information:
A43: Interest paid | B43: $ | C43: 2,019 | D43: $ | E43: 3,127 | F43: $ | G43: 2,614
A44: Income taxes paid, net of refunds | B44: $ | C44: 409,003 | D44: $ | E44: 285,891 | F44: $ | G44: 257,514
A45: Purchase of property and equipment through settlement of deposit | B45: $ | C45: 64,050 | D45: $ | E45: — | F45: $ | G45: —

Sheet 2025 k - service revenues
A1: Service revenues
A2: United States | B2: $ | C2: 3,451,558 | D2: $ | E2: 3,126,102 | F2: $ | G2: 2,841,641
A3: International | C3: 517,104 | E3: 434,900 | G3: 356,487
A4: Total service revenues | B4: $ | C4: 3,968,662 | D4: $ | E4: 3,561,002 | F4: $ | G4: 3,198,128

Sheet 2025 k - vehicle sales
A1: Vehicle sales
A2: United States | B2: $ | C2: 403,546 | D2: $ | E2: 338,633 | F2: $ | G2: 348,007
A3: International | C3: 274,750 | E3: 337,188 | G3: 323,383
A4: Total vehicle sales | B4: $ | C4: 678,296 | D4: $ | E4: 675,821 | F4: $ | G4: 671,390

Sheet 2025 k - PPE
A1: Land | B1: $ | C1: 2,394,553 | D1: $ | E1: 2,027,639
A2: Buildings and improvements | C2: 1,684,171 | E2: 1,482,891
A3: Transportation and other equipment | C3: 580,029 | E3: 604,977
A4: Office furniture and equipment | C4: 100,894 | E4: 97,576
A5: Internal-use software | C5: 120,031 | E5: 105,001
C6: 4,879,678 | E6: 4,318,084
A7: Less: Accumulated depreciation and amortization | C7: (1,281,585) | E7: (1,142,246)
A8: Property and equipment, net | B8: $ | C8: 3,598,093 | D8: $ | E8: 3,175,838

Sheet 2025 k - lease amounts 0
A1: Operating lease expense | C1: $ | D1: 28,383 | E1: $ | F1: 26,222
A2: Finance lease expense:
A3: Amortization of right-of-use assets | D3: 101 | F3: 14
A4: Interest on finance lease liabilities | D4: 249 | F4: —
A5: Short-term lease expense | D5: 6,627 | F5: 4,371
A6: Variable lease expense | D6: 1,407 | F6: 1,359
A7: Total lease expense | C7: $ | D7: 36,767 | E7: $ | F7: 31,966

Sheet 2025 k - lease amounts
A1: Operating lease right-of-use assets | B1: Operating lease right-of-use assets | C1: $ | D1: 99,708 | E1: $ | F1: 116,301
A2: Finance lease right-of-use assets | B2: Property and equipment, net | D2: 2,648 | F2: —
A3: Total lease assets, net | C3: $ | D3: 102,356 | E3: $ | F3: 116,301
A5: Operating lease liabilities - current | B5: Current portion of operating and finance lease liabilities | C5: $ | D5: 19,810 | E5: $ | F5: 21,304
A6: Finance lease liabilities - current | B6: Current portion of operating and finance lease liabilities | D6: 59 | F6: —
A7: Operating lease liabilities - non-current | B7: Operating and finance lease liabilities, net of current portion | D7: 81,224 | F7: 97,429
A8: Finance lease liabilities - non-current | B8: Operating and finance lease liabilities, net of current portion | D8: 2,646 | F8: —
A9: Total lease liabilities | C9: $ | D9: 103,739 | E9: $ | F9: 118,733

Sheet 2025 k - lease weights
B1: Weighted-Average Remaining Lease Term (In years) | C1: Weighted-Average Discount Rate (1)
A2: Operating leases | B2: 8.52 | C2: 4.29 | D2: %
A3: Finance leases | B3: 30.35 | C3: 4.48 | D3: %

Sheet 2025 k - ROU
A1: Cash paid for amounts included in the measurement of lease liabilities
A2: Operating cash flows related to operating leases | B2: $ | C2: 28,026 | D2: $ | E2: 25,320
A3: Operating cash flows related to finance leases | C3: 260 | E3: —
A4: Financing cash flows related to finance leases | C4: 49 | E4: 14
A5: Right-of-use assets obtained in exchange for new operating lease liabilities | C5: 9,516 | E5: 37,172
A6: Right-of-use assets obtained in exchange for new finance lease liabilities | C6: 2,653 | E6: —

Sheet 2025 k - PV of lease liabilitie
A1: 2026 | C1: $ | D1: 135 | E1: $ | F1: 22,407
A2: 2027 | D2: 135 | F2: 18,104
A3: 2028 | D3: 135 | F3: 16,625
A4: 2029 | D4: 135 | F4: 13,956
A5: 2030 | D5: 135 | F5: 8,534
A6: Thereafter | D6: 4,536 | F6: 39,670
A7: Total future lease commitments | C7: $ | D7: 5,211 | E7: $ | F7: 119,296
A8: Less: imputed interest | D8: (2,506) | F8: (18,262)
A9: Present value of lease liabilities | C9: $ | D9: 2,705 | E9: $ | F9: 101,034

Sheet 2025 k - future lease payments
A1: 2026 | B1: $ | C1: 5,077
A2: 2027 | C2: 5,093
A3: 2028 | C3: 4,361
A4: 2029 | C4: 3,263
A5: 2030 | C5: 27
A6: Thereafter | C6: 135
A7: Total future lease payments receivable | B7: $ | C7: 17,956

Sheet 2025 k - Future Intangibles
A1: 2026 | D1: $ | F1: (12,784)
A2: 2027 | F2: (12,651)
A3: 2028 | F3: (11,659)
A4: 2029 | F4: (2,066)
A5: 2030 | F5: (1,678)
A6: Thereafter | F6: (5,233)
A7: Total future intangible amortization expense | D7: $ | F7: (46,071)

Sheet 2025 k - Shares
A1: Weighted average common shares outstanding | B1: 965,306 | C1: 960,739 | D1: 953,574
A2: Effect of dilutive securities | B2: 12,257 | C2: 14,059 | D2: 13,073
A3: Weighted average common and dilutive potential common shares outstanding | B3: 977,563 | C3: 974,798 | D3: 966,647

Sheet 2025 k - Unvested Sahres
A1: Unvested shares at July 31, 2024 | C1: 4,178 | D1: $ | E1: 9.80
A2: Grants of non-vested shares | C2: 159 | E2: 20.58
A3: Vested | C3: (2,226) | E3: 10.73
A4: Forfeitures or expirations | C4: (22) | E4: 1.03
A5: Unvested shares at July 31, 2025 | C5: 2,089 | D5: $ | E5: 14.30

Sheet 2025 k - Options0
A1: Outstanding as of July 31, 2024 | B1: 16,310 | C1: $ | D1: 18.60 | F1: 4.34 | G1: $ | H1: 550,115
A2: Grants of options | B2: 159 | D2: 58.34
A3: Exercises | B3: (3,961) | D3: 10.79
A4: Forfeitures or expirations | B4: (21) | D4: 4.41
A5: Outstanding as of July 31, 2025 | B5: 12,487 | C5: $ | D5: 21.61 | F5: 3.87 | G5: $ | H5: 302,750
A6: Exercisable as of July 31, 2025 | B6: 11,069 | C6: $ | D6: 19.21 | F6: 3.42 | G6: $ | H6: 291,821
A7: Vested and expected to vest as of July 31, 2025 | B7: 12,481 | C7: $ | D7: 21.61 | F7: 3.87 | G7: $ | H7: 302,636

Sheet 2025 k - Options1
A1: Outstanding as of July 31, 2024 | B1: 5,995 | C1: $ | D1: 24.70 | E1: 6.47 | F1: $ | G1: 165,656
A2: Grants of options | B2: — | D2: —
A3: Exercises | B3: — | D3: —
A4: Forfeitures or expirations | B4: — | D4: —
A5: Outstanding as of July 31, 2025 | B5: 5,995 | C5: $ | D5: 24.70 | E5: 5.47 | F5: $ | G5: 124,108
A6: Exercisable as of July 31, 2025 | B6: 5,302 | C6: $ | D6: 23.64 | E6: 5.28 | F6: $ | G6: 115,169
A7: Vested and expected to vest as of July 31, 2025 | B7: 5,994 | C7: $ | D7: 24.70 | E7: 5.47 | F7: $ | G7: 124,085

Sheet 2025 k - Options
A1: Service revenues | C1: $ | D1: 3,451,558 | E1: $ | F1: 517,104 | G1: $ | H1: 3,968,662
A2: Vehicle sales | D2: 403,546 | F2: 274,750 | H2: 678,296
A3: Total service revenues and vehicle sales | D3: 3,855,104 | F3: 791,854 | H3: 4,646,958
A4: Facility operations | D4: 1,646,183 | F4: 298,135 | H4: 1,944,318
A5: Cost of vehicle sales | D5: 378,100 | F5: 224,897 | H5: 602,997
A6: General and administrative | D6: 349,935 | F6: 52,994 | H6: 402,929
A7: Operating income | C7: $ | D7: 1,480,886 | E7: $ | F7: 215,828 | G7: $ | H7: 1,696,714
A9: Depreciation and amortization, excluding debt costs | C9: $ | D9: 184,026 | E9: $ | F9: 31,823 | G9: $ | H9: 215,849
A10: Interest income | D10: 168,641 | F10: 10,268 | H10: 178,909
A11: Capital expenditures, including acquisitions | D11: 490,965 | F11: 79,248 | H11: 570,213
A12: Total assets | D12: 8,834,063 | F12: 1,256,839 | H12: 10,090,902
A13: Goodwill | D13: 390,422 | F13: 127,357 | H13: 517,779

Sheet 2025 k - T58
A1: Service revenues | D1: $ | E1: 3,126,102 | F1: $ | G1: 434,900 | H1: $ | I1: 3,561,002
A2: Vehicle sales | E2: 338,633 | G2: 337,188 | I2: 675,821
A3: Total service revenues and vehicle sales | E3: 3,464,735 | G3: 772,088 | I3: 4,236,823
A4: Facility operations | E4: 1,440,707 | G4: 269,377 | I4: 1,710,084
A5: Cost of vehicle sales | E5: 313,449 | G5: 306,038 | I5: 619,487
A6: General and administrative | E6: 282,545 | G6: 52,684 | I6: 335,229
A7: Operating income | D7: $ | E7: 1,428,034 | F7: $ | G7: 143,989 | H7: $ | I7: 1,572,023
A9: Depreciation and amortization, excluding debt costs | D9: $ | E9: 161,685 | F9: $ | G9: 28,076 | H9: $ | I9: 189,761
A10: Interest income | E10: 140,728 | G10: 4,945 | I10: 145,673
A11: Capital expenditures, including acquisitions | E11: 491,497 | G11: 113,906 | I11: 605,403
A12: Total assets | E12: 7,386,103 | G12: 1,041,661 | I12: 8,427,764
A13: Goodwill | E13: 390,421 | G13: 123,488 | I13: 513,909

Sheet 2025 k - T59
A1: Service revenues | B1: $ | C1: 2,841,641 | D1: $ | E1: 356,487 | F1: $ | G1: 3,198,128
A2: Vehicle sales | C2: 348,007 | E2: 323,383 | G2: 671,390
A3: Total service revenues and vehicle sales | C3: 3,189,648 | E3: 679,870 | G3: 3,869,518
A4: Facility operations | C4: 1,292,527 | E4: 225,502 | G4: 1,518,029
A5: Cost of vehicle sales | C5: 326,764 | E5: 287,734 | G5: 614,498
A6: General and administrative | C6: 202,260 | E6: 48,162 | G6: 250,422
A7: Operating income | B7: $ | C7: 1,368,097 | D7: $ | E7: 118,472 | F7: $ | G7: 1,486,569
A9: Depreciation and amortization, excluding debt costs | B9: $ | C9: 135,804 | D9: $ | E9: 23,674 | F9: $ | G9: 159,478
A10: Interest income | C10: 64,082 | E10: 1,846 | G10: 65,928
A11: Capital expenditures, including acquisitions | C11: 373,190 | E11: 143,446 | G11: 516,636
A12: Total assets | C12: 5,825,064 | E12: 912,815 | G12: 6,737,879
A13: Goodwill | C13: 270,269 | E13: 124,020 | G13: 394,289

Sheet April Q - BS
A1: ASSETS
A2: Current assets:
A3: Cash, cash equivalents, and restricted cash | C3: $ | E3: 3,354,142 | F3: $ | G3: 2,780,531
A4: Investment in held to maturity securities | E4: 845,570 | G4: 2,008,539
A5: Accounts receivable, net of allowance for credit losses of $14,636 and $12,945, respectively | E5: 794,472 | G5: 762,811
A6: Vehicle pooling costs | E6: 117,979 | G6: 116,145
A7: Inventories | E7: 49,632 | G7: 39,661
A8: Income taxes receivable | E8: 721 | G8: 580
A9: Prepaid expenses and other assets | E9: 54,157 | G9: 46,361
A10: Total current assets | E10: 5,216,673 | G10: 5,754,628
A11: Property and equipment, net | E11: 3,715,922 | G11: 3,598,093
A12: Operating lease right-of-use assets | E12: 88,066 | G12: 99,708
A13: Intangibles, net | E13: 53,943 | G13: 62,832
A14: Goodwill | E14: 522,703 | G14: 517,779
A15: Other assets | E15: 51,729 | G15: 57,862
A16: Total assets | C16: $ | E16: 9,649,036 | F16: $ | G16: 10,090,902
A17: LIABILITIES, REDEEMABLE NONCONTROLLING INTERESTS AND STOCKHOLDERS’ EQUITY
A18: Current liabilities:
A19: Accounts payable and accrued liabilities | C19: $ | E19: 598,290 | F19: $ | G19: 591,831
A20: Deferred revenue | E20: 33,494 | G20: 30,440
A21: Income taxes payable | E21: 37,650 | G21: 41,141
A22: Current portion of operating and finance lease liabilities | E22: 15,825 | G22: 19,869
A23: Total current liabilities | E23: 685,259 | G23: 683,281
A24: Deferred income taxes | E24: 89,733 | G24: 80,625
A25: Income taxes payable | E25: 5,308 | G25: 35,635
A26: Operating and finance lease liabilities, net of current portion | E26: 77,291 | G26: 83,870
A27: Total liabilities | E27: 857,591 | G27: 883,411
A28: Commitments and contingencies
A29: Redeemable non controlling interest | E29: 17,181 | G29: 20,458
A30: Stockholders’ equity:
A31: Preferred stock: $0.0001 par value - 5,000,000 shares authorized; none issued | E31: - | G31: -
A32: Common stock: $0.0001 par value - 1,600,000,000 shares authorized; 925,811,482 and 967,478,690 shares issued and outstanding, respectively. | E32: 93 | G32: 97
A33: Additional paid-in capital | E33: 1,207,201 | G33: 1,214,150
A34: Accumulated other comprehensive loss | E34: (87,207) | G34: (120,283)
A35: Retained earnings | E35: 7,654,177 | G35: 8,093,069
A36: Total stockholders’ equity | E36: 8,774,264 | G36: 9,187,033
A37: Total liabilities, redeemable noncontrolling interests and stockholders’ equity | C37: $ | E37: 9,649,036 | F37: $ | G37: 10,090,902

Sheet April Q - IS
A1: Service revenues and vehicle sales:
A2: Service revenues | B2: $ | C2: 1,056,080 $ | D2: 1,034,836 $ | E2: 2,999,976 $ | F2: 3,012,453
A3: Vehicle sales | C3: 180,986 | D3: 176,880 | E3: 513,794 | F3: 509,408
A4: Total service revenues and vehicle sales | C4: 1,237,066 | D4: 1,211,716 | E4: 3,513,770 | F4: 3,521,861
A5: Operating expenses:
A6: Facility operations | C6: 504,190 | D6: 489,735 | E6: 1,459,109 | F6: 1,476,337
A7: Cost of vehicle sales | C7: 160,277 | D7: 169,714 | E7: 452,252 | F7: 455,599
A8: General and administrative | C8: 108,317 | D8: 100,722 | E8: 318,723 | F8: 305,802
A9: Total operating expenses | C9: 772,784 | D9: 760,171 | E9: 2,230,084 | F9: 2,237,738
A10: Operating income | C10: 464,282 | D10: 451,545 | E10: 1,283,686 | F10: 1,284,123
A11: Other income (expense):
A12: Interest income, net | C12: 38,813 | D12: 42,776 | E12: 142,305 | F12: 129,070
A13: Other (expense) income, net | C13: (1,001) | D13: 8,483 | E13: 4,275 | F13: 3,980
A14: Total other income | C14: 37,812 | D14: 51,259 | E14: 146,580 | F14: 133,050
A15: Income before income taxes | C15: 502,094 | D15: 502,804 | E15: 1,430,266 | F15: 1,417,173
A16: Income tax expense | C16: 100,701 | D16: 97,466 | E16: 276,696 | F16: 264,118
A17: Net income | C17: 401,393 | D17: 405,338 | E17: 1,153,570 | F17: 1,153,055
A18: Less: Net loss attributable to redeemable noncontrolling interest | C18: (1,008) | D18: (1,271) | E18: (3,277) | F18: (3,040)
A19: Net income attributable to Copart, Inc. | B19: $ | C19: 402,401 $ | D19: 406,609 $ | E19: 1,156,847 $ | F19: 1,156,095
A21: Basic net income per common share | B21: $ | C21: 0.43 $ | D21: 0.42 $ | E21: 1.21 $ | F21: 1.20
A22: Weighted average common shares outstanding | C22: 936,293 | D22: 966,234 | E22: 957,280 | F22: 964,702
A24: Diluted net income per common share | B24: $ | C24: 0.43 $ | D24: 0.42 $ | E24: 1.20 $ | F24: 1.18
A25: Diluted weighted average common shares outstanding | C25: 942,770 | D25: 978,089 | E25: 965,215 | F25: 977,485

Sheet April Q - Shares
A1: Weighted average common shares outstanding | C1: 936,293 | D1: 966,234 | E1: 957,280 | F1: 964,702
A2: Effect of dilutive securities | C2: 6,477 | D2: 11,855 | E2: 7,935 | F2: 12,783
A3: Weighted average common and dilutive potential common shares outstanding | C3: 942,770 | D3: 978,089 | E3: 965,215 | F3: 977,485

Sheet April Q - T14
A1: Outstanding as of July 31, 2025 | C1: 12,487 $ | D1: 21.61 | E1: 5,995 $ | F1: 24.70
A2: Grants of options | C2: 746 | D2: 44.56 | E2: 75 | F2: 46.57
A3: Exercises | C3: (1,345) | D3: 10.53 | E3: — | F3: —
A4: Forfeitures or expirations | C4: (476) | D4: 47.95 | E4: — | F4: —
A5: Outstanding as of April 30, 2026 | C5: 11,412 $ | D5: 23.32 | E5: 6,070 $ | F5: 24.97
A6: Exercisable as of April 30, 2026 | C6: 10,354 $ | D6: 21.32 | E6: 5,596 $ | F6: 24.06

Sheet April Q - T15
A1: Outstanding as of July 31, 2025 | F1: 1,778 | G1: $ | I1: 48.93
A2: Grants | F2: 596 | I2: 45.05
A3: Vested | F3: (208) | I3: 40.15
A4: Forfeitures or expirations | F4: (245) | I4: 49.84
A5: Outstanding as of April 30, 2026 | F5: 1,921 | G5: $ | I5: 47.77

Sheet April Q - T16
A1: Service revenues | B1: $ | C1: 895,464 $ | D1: 160,616 $ | E1: 1,056,080 $ | F1: 898,625 $ | G1: 136,211 $ | H1: 1,034,836
A2: Vehicle sales | C2: 107,398 | D2: 73,588 | E2: 180,986 | F2: 107,832 | G2: 69,048 | H2: 176,880
A3: Total service revenues and vehicle sales | C3: 1,002,862 | D3: 234,204 | E3: 1,237,066 | F3: 1,006,457 | G3: 205,259 | H3: 1,211,716
A4: Facility operations | C4: 419,714 | D4: 84,476 | E4: 504,190 | F4: 412,895 | G4: 76,840 | H4: 489,735
A5: Cost of vehicle sales | C5: 99,024 | D5: 61,253 | E5: 160,277 | F5: 113,853 | G5: 55,861 | H5: 169,714
A6: General and administrative | C6: 93,679 | D6: 14,638 | E6: 108,317 | F6: 87,244 | G6: 13,478 | H6: 100,722
A7: Operating income | B7: $ | C7: 390,445 $ | D7: 73,837 $ | E7: 464,282 $ | F7: 392,465 $ | G7: 59,080 $ | H7: 451,545
A9: Depreciation and amortization, excluding debt issuance costs | B9: $ | C9: 50,259 $ | D9: 8,724 $ | E9: 58,983 $ | F9: 46,461 $ | G9: 7,955 $ | H9: 54,416
A10: Interest income, net | C10: 35,439 | D10: 3,374 | E10: 38,813 | F10: 39,262 | G10: 3,514 | H10: 42,776
A11: Capital expenditures and acquisitions | C11: 75,213 | D11: 5,733 | E11: 80,946 | F11: 62,906 | G11: 7,561 | H11: 70,467

Sheet April Q - T17
A1: Service revenues | B1: $ | C1: 2,570,465 $ | D1: 429,511 $ | E1: 2,999,976 $ | F1: 2,626,745 $ | G1: 385,708 $ | H1: 3,012,453
A2: Vehicle sales | C2: 306,631 | D2: 207,163 | E2: 513,794 | F2: 302,097 | G2: 207,311 | H2: 509,408
A3: Total service revenues and vehicle sales | C3: 2,877,096 | D3: 636,674 | E3: 3,513,770 | F3: 2,928,842 | G3: 593,019 | H3: 3,521,861
A4: Facility operations | C4: 1,213,549 | D4: 245,560 | E4: 1,459,109 | F4: 1,255,336 | G4: 221,001 | H4: 1,476,337
A5: Cost of vehicle sales | C5: 285,356 | D5: 166,896 | E5: 452,252 | F5: 282,946 | G5: 172,653 | H5: 455,599
A6: General and administrative | C6: 271,301 | D6: 47,422 | E6: 318,723 | F6: 267,142 | G6: 38,660 | H6: 305,802
A7: Operating income | B7: $ | C7: 1,106,890 $ | D7: 176,796 $ | E7: 1,283,686 $ | F7: 1,123,418 $ | G7: 160,705 $ | H7: 1,284,123
A9: Depreciation and amortization, excluding debt issuance costs | B9: $ | C9: 142,497 $ | D9: 25,915 $ | E9: 168,412 $ | F9: 138,831 $ | G9: 23,411 $ | H9: 162,242
A10: Interest income, net | C10: 132,492 | D10: 9,813 | E10: 142,305 | F10: 122,254 | G10: 6,816 | H10: 129,070
A11: Capital expenditures and acquisitions | C11: 205,546 | D11: 57,754 | E11: 263,300 | F11: 428,035 | G11: 54,527 | H11: 482,562

Sheet April Q - % of rev
A1: Service revenues and vehicle sales:
A2: Service revenues | D2: 85% | F2: 85% | H2: 85% | K2: 86%
A3: Vehicle sales | D3: 15% | F3: 15% | H3: 15% | K3: 14%
A4: Total service revenues and vehicle sales | D4: 100% | F4: 100% | H4: 100% | K4: 100%
A6: Operating expenses:
A7: Facility operations | D7: 40% | F7: 41% | H7: 41% | K7: 42%
A8: Cost of vehicle sales | D8: 13% | F8: 14% | H8: 13% | K8: 13%
A9: General and administrative | D9: 9% | F9: 8% | H9: 9% | K9: 9%
A10: Total operating expenses | D10: 62% | F10: 63% | H10: 63% | K10: 64%
A11: Operating income | D11: 38% | F11: 37% | H11: 37% | K11: 36%
A12: Other income (expense) | D12: 3% | F12: 4% | H12: 4% | K12: 4%
A13: Income before income taxes | D13: 41% | F13: 41% | H13: 41% | K13: 40%
A14: Income taxes | D14: 8% | F14: 8% | H14: 8% | K14: 7%
A15: Net income | D15: 33% | F15: 33% | H15: 33% | K15: 33%

Sheet April Q - service rev
A1: Service revenues
A2: United States | B2: $ | C2: 895,464 $ | D2: 898,625 $ | E2: (3,161) | F2: (0.4)% $ | G2: 2,570,465 $ | H2: 2,626,745 $ | I2: (56,280) | J2: (2.1)%
A3: International | C3: 160,616 | D3: 136,211 $ | E3: 24,405 | F3: 17.9% | G3: 429,511 | H3: 385,708 $ | I3: 43,803 | J3: 11.4%
A4: Total service revenues | B4: $ | C4: 1,056,080 $ | D4: 1,034,836 $ | E4: 21,244 | F4: 2.1% $ | G4: 2,999,976 $ | H4: 3,012,453 $ | I4: (12,477) | J4: (0.4)%

Sheet April Q - vehicle sales
A1: Vehicle sales
A2: United States | B2: $ | C2: 107,398 $ | D2: 107,832 $ | E2: (434) | F2: (0.4)% $ | G2: 306,631 $ | H2: 302,097 $ | I2: 4,534 | J2: 1.5%
A3: International | C3: 73,588 | D3: 69,048 $ | E3: 4,540 | F3: 6.6% $ | G3: 207,163 | H3: 207,311 $ | I3: (148) | J3: (0.1)%
A4: Total vehicle sales | B4: $ | C4: 180,986 $ | D4: 176,880 $ | E4: 4,106 | F4: 2.3% $ | G4: 513,794 $ | H4: 509,408 $ | I4: 4,386 | J4: 0.9%

Sheet April Q - Cost of vehicle sal
A1: Cost of vehicle sales
A2: United States | B2: $ | C2: 99,024 $ | D2: 113,853 $ | E2: (14,829) | F2: (13.0)% $ | G2: 285,356 $ | H2: 282,946 $ | I2: 2,410 | J2: 0.9%
A3: International | C3: 61,253 | D3: 55,861 | E3: 5,392 | F3: 9.7% | G3: 166,896 | H3: 172,653 | I3: (5,757) | J3: (3.3)%
A4: Total cost of vehicle sales | B4: $ | C4: 160,277 $ | D4: 169,714 $ | E4: (9,437) | F4: (5.6)% $ | G4: 452,252 $ | H4: 455,599 $ | I4: (3,347) | J4: (0.7)%

Sheet january Q - BS
A1: ASSETS
A2: Current assets:
A3: Cash, cash equivalents, and restricted cash | C3: $ | E3: 5,101,821 | F3: $ | G3: 2,780,531
A4: Investment in held to maturity securities | E4: - | G4: 2,008,539
A5: Accounts receivable, net of allowance for credit losses of $14,916 and $12,945, respectively | E5: 861,630 | G5: 762,811
A6: Vehicle pooling costs | E6: 129,763 | G6: 116,145
A7: Inventories | E7: 41,870 | G7: 39,661
A8: Income taxes receivable | E8: 817 | G8: 580
A9: Prepaid expenses and other assets | E9: 40,279 | G9: 46,361
A10: Total current assets | E10: 6,176,180 | G10: 5,754,628
A11: Property and equipment, net | E11: 3,693,890 | G11: 3,598,093
A12: Operating lease right-of-use assets | E12: 91,454 | G12: 99,708
A13: Intangibles, net | E13: 57,292 | G13: 62,832
A14: Goodwill | E14: 523,473 | G14: 517,779
A15: Other assets | E15: 52,673 | G15: 57,862
A16: Total assets | C16: $ | E16: 10,594,962 | F16: $ | G16: 10,090,902
A17: LIABILITIES, REDEEMABLE NONCONTROLLING INTERESTS AND STOCKHOLDERS’ EQUITY
A18: Current liabilities:
A19: Accounts payable and accrued liabilities | C19: $ | E19: 549,171 | F19: $ | G19: 591,831
A20: Deferred revenue | E20: 31,383 | G20: 30,440
A21: Income taxes payable | E21: 16,627 | G21: 41,141
A22: Current portion of operating and finance lease liabilities | E22: 16,692 | G22: 19,869
A23: Total current liabilities | E23: 613,873 | G23: 683,281
A24: Deferred income taxes | E24: 87,625 | G24: 80,625
A25: Income taxes payable | E25: 6,786 | G25: 35,635
A26: Operating and finance lease liabilities, net of current portion | E26: 79,444 | G26: 83,870
A27: Total liabilities | E27: 787,728 | G27: 883,411
A28: Commitments and contingencies
A29: Redeemable non-controlling interest | E29: 18,189 | G29: 20,458
A30: Stockholders’ equity:
A31: Preferred stock: $0.0001 par value - 5,000,000 shares authorized; none issued | E31: - | G31: -
A32: Common stock: $0.0001 par value - 1,600,000,000 shares authorized; 963,290,932 and 967,478,690 shares issued and outstanding, respectively. | E32: 96 | G32: 97
A33: Additional paid-in capital | E33: 1,242,164 | G33: 1,214,150
A34: Accumulated other comprehensive loss | E34: (87,291) | G34: (120,283)
A35: Retained earnings | E35: 8,634,076 | G35: 8,093,069
A36: Total stockholders’ equity | E36: 9,789,045 | G36: 9,187,033
A37: Total liabilities, redeemable noncontrolling interests and stockholders’ equity | C37: $ | E37: 10,594,962 | F37: $ | G37: 10,090,902

Sheet january Q - IS
A1: Service revenues and vehicle sales:
A2: Service revenues | B2: $ | C2: 952,051 $ | D2: 991,281 $ | E2: 1,943,896 $ | F2: 1,977,617
A3: Vehicle sales | C3: 169,623 | D3: 172,035 | E3: 332,808 | F3: 332,528
A4: Total service revenues and vehicle sales | C4: 1,121,674 | D4: 1,163,316 | E4: 2,276,704 | F4: 2,310,145
A5: Operating expenses:
A6: Facility operations | C6: 478,430 | D6: 490,056 | E6: 954,919 | F6: 986,602
A7: Cost of vehicle sales | C7: 150,432 | D7: 147,707 | E7: 291,975 | F7: 285,885
A8: General and administrative | C8: 104,102 | D8: 99,342 | E8: 210,406 | F8: 205,080
A9: Total operating expenses | C9: 732,964 | D9: 737,105 | E9: 1,457,300 | F9: 1,477,567
A10: Operating income | C10: 388,710 | D10: 426,211 | E10: 819,404 | F10: 832,578
A11: Other income (expense):
A12: Interest income, net | C12: 49,987 | D12: 40,747 | E12: 103,492 | F12: 86,294
A13: Other income (expense), net | C13: 2,352 | D13: (3,907) | E13: 5,276 | F13: (4,503)
A14: Total other income | C14: 52,339 | D14: 36,840 | E14: 108,768 | F14: 81,791
A15: Income before income taxes | C15: 441,049 | D15: 463,051 | E15: 928,172 | F15: 914,369
A16: Income tax expense | C16: 91,082 | D16: 76,510 | E16: 175,995 | F16: 166,652
A17: Net income | C17: 349,967 | D17: 386,541 | E17: 752,177 | F17: 747,717
A18: Less: Net loss attributable to redeemable noncontrolling interest | C18: (765) | D18: (859) | E18: (2,269) | F18: (1,769)
A19: Net income attributable to Copart, Inc. | B19: $ | C19: 350,732 $ | D19: 387,400 $ | E19: 754,446 $ | F19: 749,486
A21: Basic net income per common share | B21: $ | C21: 0.36 $ | D21: 0.40 $ | E21: 0.78 $ | F21: 0.78
A22: Weighted average common shares outstanding | C22: 967,212 | D22: 964,746 | E22: 967,431 | F22: 963,961
A24: Diluted net income per common share | B24: $ | C24: 0.36 $ | D24: 0.40 $ | E24: 0.77 $ | F24: 0.77
A25: Diluted weighted average common shares outstanding | C25: 975,089 | D25: 977,910 | E25: 976,095 | F25: 977,208

Sheet january Q - shares
A1: Weighted average common shares outstanding | C1: 967,212 | D1: 964,746 | E1: 967,431 | F1: 963,961
A2: Effect of dilutive securities | C2: 7,877 | D2: 13,164 | E2: 8,664 | F2: 13,247
A3: Weighted average common and dilutive potential common shares outstanding | C3: 975,089 | D3: 977,910 | E3: 976,095 | F3: 977,208

Sheet january Q - T16
A1: Service revenues | B1: $ | C1: 819,467 $ | D1: 132,584 $ | E1: 952,051 $ | F1: 868,130 $ | G1: 123,151 $ | H1: 991,281
A2: Vehicle sales | C2: 102,153 | D2: 67,470 | E2: 169,623 | F2: 106,715 | G2: 65,320 | H2: 172,035
A3: Total service revenues and vehicle sales | C3: 921,620 | D3: 200,054 | E3: 1,121,674 | F3: 974,845 | G3: 188,471 | H3: 1,163,316
A4: Facility operations | C4: 395,350 | D4: 83,080 | E4: 478,430 | F4: 418,824 | G4: 71,232 | H4: 490,056
A5: Cost of vehicle sales | C5: 96,375 | D5: 54,057 | E5: 150,432 | F5: 92,807 | G5: 54,900 | H5: 147,707
A6: General and administrative | C6: 88,423 | D6: 15,679 | E6: 104,102 | F6: 87,321 | G6: 12,021 | H6: 99,342
A7: Operating income | B7: $ | C7: 341,472 $ | D7: 47,238 $ | E7: 388,710 $ | F7: 375,893 $ | G7: 50,318 $ | H7: 426,211
A9: Depreciation and amortization, excluding debt costs | B9: $ | C9: 46,829 $ | D9: 8,558 $ | E9: 55,387 $ | F9: 46,455 $ | G9: 7,744 $ | H9: 54,199
A10: Interest income | C10: 46,958 | D10: 3,029 | E10: 49,987 | F10: 39,149 | G10: 1,598 | H10: 40,747
A11: Capital expenditures and acquisitions | C11: 58,875 | D11: 10,738 | E11: 69,613 | F11: 153,212 | G11: 20,868 | H11: 174,080

Sheet january Q - T17
A1: Service revenues | B1: $ | C1: 1,675,001 $ | D1: 268,895 $ | E1: 1,943,896 $ | F1: 1,728,120 $ | G1: 249,497 $ | H1: 1,977,617
A2: Vehicle sales | C2: 199,233 | D2: 133,575 | E2: 332,808 | F2: 194,265 | G2: 138,263 | H2: 332,528
A3: Total service revenues and vehicle sales | C3: 1,874,234 | D3: 402,470 | E3: 2,276,704 | F3: 1,922,385 | G3: 387,760 | H3: 2,310,145
A4: Facility operations | C4: 793,835 | D4: 161,084 | E4: 954,919 | F4: 842,441 | G4: 144,161 | H4: 986,602
A5: Cost of vehicle sales | C5: 186,334 | D5: 105,641 | E5: 291,975 | F5: 169,093 | G5: 116,792 | H5: 285,885
A6: General and administrative | C6: 177,621 | D6: 32,785 | E6: 210,406 | F6: 179,898 | G6: 25,182 | H6: 205,080
A7: Operating income | B7: $ | C7: 716,444 $ | D7: 102,960 $ | E7: 819,404 $ | F7: 730,953 $ | G7: 101,625 $ | H7: 832,578
A9: Depreciation and amortization, excluding debt costs | B9: $ | C9: 92,238 $ | D9: 17,191 $ | E9: 109,429 $ | F9: 92,370 $ | G9: 15,456 $ | H9: 107,826
A10: Interest income | C10: 97,053 | D10: 6,439 | E10: 103,492 | F10: 82,992 | G10: 3,302 | H10: 86,294
A11: Capital expenditures and acquisitions | C11: 130,333 | D11: 52,021 | E11: 182,354 | F11: 365,129 | G11: 46,966 | H11: 412,095

Sheet january Q - % of rev
A1: Service revenues and vehicle sales:
A2: Service revenues | D2: 85% | F2: 85% | H2: 85% | K2: 86%
A3: Vehicle sales | D3: 15% | F3: 15% | H3: 15% | K3: 14%
A4: Total service revenues and vehicle sales | D4: 100% | F4: 100% | H4: 100% | K4: 100%
A6: Operating expenses:
A7: Facility operations | D7: 43% | F7: 42% | H7: 42% | K7: 43%
A8: Cost of vehicle sales | D8: 13% | F8: 13% | H8: 13% | K8: 12%
A9: General and administrative | D9: 9% | F9: 9% | H9: 9% | K9: 9%
A10: Total operating expenses | D10: 65% | F10: 64% | H10: 64% | K10: 64%
A11: Operating income | D11: 35% | F11: 36% | H11: 36% | K11: 36%
A12: Other income (expense) | D12: 5% | F12: 3% | H12: 5% | K12: 4%
A13: Income before income taxes | D13: 40% | F13: 39% | H13: 41% | K13: 40%
A14: Income taxes | D14: 8% | F14: 6% | H14: 8% | K14: 7%
A15: Net income | D15: 32% | F15: 33% | H15: 33% | K15: 33%

Sheet january Q - service revenues
A1: Service revenues
A2: United States | B2: $ | C2: 819,467 $ | D2: 868,130 $ | E2: (48,663) | F2: (5.6)% $ | G2: 1,675,001 $ | H2: 1,728,120 $ | I2: (53,119) | J2: (3.1)%
A3: International | C3: 132,584 | D3: 123,151 $ | E3: 9,433 | F3: 7.7% | G3: 268,895 | H3: 249,497 $ | I3: 19,398 | J3: 7.8%
A4: Total service revenues | B4: $ | C4: 952,051 $ | D4: 991,281 $ | E4: (39,230) | F4: (4.0)% $ | G4: 1,943,896 $ | H4: 1,977,617 $ | I4: (33,721) | J4: (1.7)%

Sheet january Q - vehicle Sales
A1: Vehicle sales
A2: United States | B2: $ | C2: 102,153 $ | D2: 106,715 $ | E2: (4,562) | F2: (4.3)% $ | G2: 199,233 $ | H2: 194,265 $ | I2: 4,968 | J2: 2.6%
A3: International | C3: 67,470 | D3: 65,320 $ | E3: 2,150 | F3: 3.3% $ | G3: 133,575 | H3: 138,263 $ | I3: (4,688) | J3: (3.4)%
A4: Total vehicle sales | B4: $ | C4: 169,623 $ | D4: 172,035 $ | E4: (2,412) | F4: (1.4)% $ | G4: 332,808 $ | H4: 332,528 $ | I4: 280 | J4: 0.1%

Sheet january Q - COst of vehicle sal
A1: Cost of vehicle sales
A2: United States | B2: $ | C2: 96,375 $ | D2: 92,807 $ | E2: 3,568 | F2: 3.8% $ | G2: 186,334 $ | H2: 169,093 $ | I2: 17,241 | J2: 10.2%
A3: International | C3: 54,057 | D3: 54,900 | E3: (843) | F3: (1.5)% | G3: 105,641 | H3: 116,792 | I3: (11,151) | J3: (9.5)%
A4: Total cost of vehicle sales | B4: $ | C4: 150,432 $ | D4: 147,707 $ | E4: 2,725 | F4: 1.8% $ | G4: 291,975 $ | H4: 285,885 $ | I4: 6,090 | J4: 2.1%

Sheet October Q - BS
A1: ASSETS
A2: Current assets:
A3: Cash, cash equivalents, and restricted cash | C3: $ | E3: 5,233,590 | F3: $ | G3: 2,780,53 1
A4: Investment in held to maturity securities | E4: 9,861 | G4: 2,008,539
A5: Accounts receivable, net of allowance for credit losses of $14,916 and $12,945, respectively | E5: 759,687 | G5: 762,811
A6: Vehicle pooling costs | E6: 118,166 | G6: 116,145
A7: Inventories | E7: 40,408 | G7: 39,661
A8: Income taxes receivable | E8: 574 | G8: 580
A9: Prepaid expenses and other assets | E9: 39,848 | G9: 46,361
A10: Total current assets | E10: 6,202,134 | G10: 5,754,628
A11: Property and equipment, net | E11: 3,650,424 | G11: 3,598,093
A12: Operating lease right-of-use assets | E12: 95,594 | G12: 99,708
A13: Intangibles, net | E13: 59,615 | G13: 62,832
A14: Goodwill | E14: 518,756 | G14: 517,779
A15: Other assets | E15: 54,491 | G15: 57,862
A16: Total assets | C16: $ | E16: 10,581,014 | F16: $ | G16: 10,090,902
A17: LIABILITIES, REDEEMABLE NONCONTROLLING INTERESTS AND STOCKHOLDERS’ EQUITY
A18: Current liabilities:
A19: Accounts payable and accrued liabilities | C19: $ | E19: 607,386 | F19: $ | G19: 591,831
A20: Deferred revenue | E20: 30,471 | G20: 30,440
A21: Income taxes payable | E21: 125,469 | G21: 41,141
A22: Current portion of operating and finance lease liabilities | E22: 17,870 | G22: 19,869
A23: Total current liabilities | E23: 781,196 | G23: 683,281
A24: Deferred income taxes | E24: 85,839 | G24: 80,625
A25: Income taxes payable | E25: 12,802 | G25: 35,635
A26: Operating and finance lease liabilities, net of current portion | E26: 82,066 | G26: 83,870
A27: Total liabilities | E27: 961,903 | G27: 883,411
A28: Commitments and contingencies
A29: Redeemable non-controlling interest | E29: 18,954 | G29: 20,458
A30: Stockholders’ equity:
A31: Preferred stock: $0.0001 par value - 5,000,000 shares authorized; none issued | E31: - | G31: -
A32: Common stock: $0.0001 par value - 1,600,000,000 shares authorized; 967,904,634 and 967,478,690 shares issued and outstanding, respectively. | E32: 97 | G32: 97
A33: Additional paid-in capital | E33: 1,224,683 | G33: 1,214,150
A34: Accumulated other comprehensive loss | E34: (120,076) | G34: (120,283)
A35: Retained earnings | E35: 8,495,453 | G35: 8,093,069
A36: Total stockholders’ equity | E36: 9,600,157 | G36: 9,187,033
A37: Total liabilities, redeemable noncontrolling interests and stockholders’ equity | C37: $ | E37: 10,581,014 | F37: $ | G37: 10,090,902

Sheet October Q - IS0
A1: Service revenues and vehicle sales:
A2: Service revenues | C2: $ | E2: 991,845 | F2: $ | H2: 986,336
A3: Vehicle sales | E3: 163,185 | H3: 160,493
A4: Total service revenues and vehicle sales | E4: 1,155,030 | H4: 1,146,829
A5: Operating expenses:
A6: Facility operations | E6: 476,489 | H6: 496,546
A7: Cost of vehicle sales | E7: 141,543 | H7: 138,178
A8: General and administrative | E8: 106,304 | H8: 105,738
A9: Total operating expenses | E9: 724,336 | H9: 740,462
A10: Operating income | E10: 430,694 | H10: 406,367
A11: Other income (expense):
A12: Interest income, net | E12: 53,505 | H12: 45,547
A13: Other income (expense), net | E13: 2,924 | H13: (596)
A14: Total other income | E14: 56,429 | H14: 44,951
A15: Income before income taxes | E15: 487,123 | H15: 451,318
A16: Income tax expense | E16: 84,913 | H16: 90,142
A17: Net income | E17: 402,210 | H17: 361,176
A18: Less: Net (loss) income attributable to redeemable noncontrolling interest | E18: (1,504) | H18: (910)
A19: Net income attributable to Copart, Inc. | C19: $ | E19: 403,714 | F19: $ | H19: 362,086
A21: Basic net income per common share | C21: $ | E21: 0.42 | F21: $ | H21: 0.38
A22: Weighted average common shares outstanding | E22: 967,650 | H22: 963,176
A24: Diluted net income per common share | C24: $ | E24: 0.41 | F24: $ | H24: 0.37
A25: Diluted weighted average common shares outstanding | E25: 977,100 | H25: 976,506

Sheet October Q - shares
A1: Weighted average common shares outstanding | E1: 967,650 | G1: 963,176
A2: Effect of dilutive securities | E2: 9,450 | G2: 13,330
A3: Weighted average common and dilutive potential common shares outstanding | E3: 977,100 | G3: 976,506

Sheet October Q - % income stat
A1: Service revenues and vehicle sales:
A2: Service revenues | D2: 86% | F2: 86%
A3: Vehicle sales | D3: 14% | F3: 14%
A4: Total service revenues and vehicle sales | D4: 100% | F4: 100%
A6: Operating expenses:
A7: Facility operations | D7: 41% | F7: 43%
A8: Cost of vehicle sales | D8: 12% | F8: 12%
A9: General and administrative | D9: 9% | F9: 9%
A10: Total operating expenses | D10: 62% | F10: 64%
A11: Operating income | D11: 38% | F11: 36%
A12: Other income (expense) | D12: 4% | F12: 3%
A13: Income before income taxes | D13: 42% | F13: 39%
A14: Income taxes | D14: 7% | F14: 8%
A15: Net income | D15: 35% | F15: 31%

Sheet October Q - service rev
A1: Service revenues
A2: United States | C2: $ | E2: 855,534 | F2: $ | H2: 859,990 | I2: $ | K2: (4,456) | M2: (0.5)%
A3: International | E3: 136,311 | H3: 126,346 | I3: $ | K3: 9,965 | M3: 7.9%
A4: Total service revenues | C4: $ | E4: 991,845 | F4: $ | H4: 986,336 | I4: $ | K4: 5,509 | M4: 0.6%

Sheet October Q - vehicle sales
A1: Vehicle sales
A2: United States | C2: $ | E2: 97,080 | F2: $ | H2: 87,549 | I2: $ | K2: 9,531 | M2: 10.9%
A3: International | C3: $ | E3: 66,105 | H3: 72,944 | I3: $ | K3: (6,839) | M3: (9.4)%
A4: Total vehicle sales | C4: $ | E4: 163,185 | F4: $ | H4: 160,493 | I4: $ | K4: 2,692 | M4: 1.7%

Sheet October Q - cost of vehicle sal
A1: Cost of vehicle sales
A2: United States | C2: $ | E2: 89,959 | F2: $ | H2: 76,286 | I2: $ | J2: 13,673 | L2: 17.9%
A3: International | E3: 51,584 | H3: 61,892 | J3: (10,308) | L3: (16.7)%
A4: Total cost of vehicle sales | C4: $ | E4: 141,543 | F4: $ | H4: 138,178 | I4: $ | J4: 3,365 | L4: 2.4%
